{
    "Meta Data": {
        "1. Information": "Monthly Adjusted Prices and Volumes",
        "2. Symbol": "DHI",
        "3. Last Refreshed": "2023-06-05",
        "4. Time Zone": "US/Eastern"
    },
    "Monthly Adjusted Time Series": {
        "2023-06-05": {
            "1. open": "107.3900",
            "2. high": "112.1300",
            "3. low": "107.2800",
            "4. close": "111.4200",
            "5. adjusted close": "111.4200",
            "6. volume": "5792360",
            "7. dividend amount": "0.0000"
        },
        "2023-05-31": {
            "1. open": "109.6400",
            "2. high": "112.8750",
            "3. low": "105.0200",
            "4. close": "106.8400",
            "5. adjusted close": "106.8400",
            "6. volume": "60358306",
            "7. dividend amount": "0.2500"
        },
        "2023-04-28": {
            "1. open": "97.3200",
            "2. high": "110.3700",
            "3. low": "94.2200",
            "4. close": "109.8200",
            "5. adjusted close": "109.5677",
            "6. volume": "65557853",
            "7. dividend amount": "0.0000"
        },
        "2023-03-31": {
            "1. open": "92.0700",
            "2. high": "99.4000",
            "3. low": "89.0500",
            "4. close": "97.6900",
            "5. adjusted close": "97.4656",
            "6. volume": "74551544",
            "7. dividend amount": "0.0000"
        },
        "2023-02-28": {
            "1. open": "98.0000",
            "2. high": "104.1400",
            "3. low": "89.8100",
            "4. close": "92.4800",
            "5. adjusted close": "92.2676",
            "6. volume": "55161462",
            "7. dividend amount": "0.2500"
        },
        "2023-01-31": {
            "1. open": "90.6400",
            "2. high": "98.9300",
            "3. low": "89.3900",
            "4. close": "98.6900",
            "5. adjusted close": "98.2132",
            "6. volume": "53832841",
            "7. dividend amount": "0.0000"
        },
        "2022-12-30": {
            "1. open": "86.9900",
            "2. high": "92.4500",
            "3. low": "82.9700",
            "4. close": "89.1400",
            "5. adjusted close": "88.7093",
            "6. volume": "56413246",
            "7. dividend amount": "0.2500"
        },
        "2022-11-30": {
            "1. open": "78.5000",
            "2. high": "86.0900",
            "3. low": "72.0400",
            "4. close": "86.0000",
            "5. adjusted close": "85.3384",
            "6. volume": "63592379",
            "7. dividend amount": "0.0000"
        },
        "2022-10-31": {
            "1. open": "68.9600",
            "2. high": "78.0600",
            "3. low": "66.0100",
            "4. close": "76.8800",
            "5. adjusted close": "76.2886",
            "6. volume": "63933538",
            "7. dividend amount": "0.0000"
        },
        "2022-09-30": {
            "1. open": "70.3800",
            "2. high": "74.8750",
            "3. low": "66.8200",
            "4. close": "67.3500",
            "5. adjusted close": "66.8319",
            "6. volume": "70144097",
            "7. dividend amount": "0.0000"
        },
        "2022-08-31": {
            "1. open": "77.7400",
            "2. high": "80.3900",
            "3. low": "71.0100",
            "4. close": "71.1500",
            "5. adjusted close": "70.6027",
            "6. volume": "47470210",
            "7. dividend amount": "0.2250"
        },
        "2022-07-29": {
            "1. open": "66.8800",
            "2. high": "79.4000",
            "3. low": "66.7500",
            "4. close": "78.0300",
            "5. adjusted close": "77.1957",
            "6. volume": "72804895",
            "7. dividend amount": "0.0000"
        },
        "2022-06-30": {
            "1. open": "75.3400",
            "2. high": "77.1400",
            "3. low": "59.2500",
            "4. close": "66.1900",
            "5. adjusted close": "65.4823",
            "6. volume": "94639274",
            "7. dividend amount": "0.0000"
        },
        "2022-05-31": {
            "1. open": "69.3100",
            "2. high": "75.9990",
            "3. low": "64.1300",
            "4. close": "75.1500",
            "5. adjusted close": "74.3465",
            "6. volume": "74846791",
            "7. dividend amount": "0.2250"
        },
        "2022-04-29": {
            "1. open": "75.6400",
            "2. high": "77.2800",
            "3. low": "68.7900",
            "4. close": "69.5900",
            "5. adjusted close": "68.6254",
            "6. volume": "79651488",
            "7. dividend amount": "0.0000"
        },
        "2022-03-31": {
            "1. open": "85.1300",
            "2. high": "88.6600",
            "3. low": "74.4700",
            "4. close": "74.5100",
            "5. adjusted close": "73.4773",
            "6. volume": "80680886",
            "7. dividend amount": "0.0000"
        },
        "2022-02-28": {
            "1. open": "89.8300",
            "2. high": "91.1500",
            "3. low": "75.5300",
            "4. close": "85.4000",
            "5. adjusted close": "84.2163",
            "6. volume": "79850843",
            "7. dividend amount": "0.2250"
        },
        "2022-01-31": {
            "1. open": "107.9100",
            "2. high": "108.6400",
            "3. low": "80.6500",
            "4. close": "89.2200",
            "5. adjusted close": "87.7519",
            "6. volume": "81709955",
            "7. dividend amount": "0.0000"
        },
        "2021-12-31": {
            "1. open": "97.3900",
            "2. high": "110.4500",
            "3. low": "97.3900",
            "4. close": "108.4500",
            "5. adjusted close": "106.6655",
            "6. volume": "68172338",
            "7. dividend amount": "0.2250"
        },
        "2021-11-30": {
            "1. open": "89.3300",
            "2. high": "104.3400",
            "3. low": "88.0700",
            "4. close": "97.7000",
            "5. adjusted close": "95.8820",
            "6. volume": "56097039",
            "7. dividend amount": "0.0000"
        },
        "2021-10-29": {
            "1. open": "84.2900",
            "2. high": "92.0000",
            "3. low": "82.3000",
            "4. close": "89.2700",
            "5. adjusted close": "87.6088",
            "6. volume": "42916803",
            "7. dividend amount": "0.0000"
        },
        "2021-09-30": {
            "1. open": "95.7200",
            "2. high": "97.7000",
            "3. low": "83.9400",
            "4. close": "83.9700",
            "5. adjusted close": "82.4075",
            "6. volume": "59886180",
            "7. dividend amount": "0.0000"
        },
        "2021-08-31": {
            "1. open": "96.5700",
            "2. high": "99.6503",
            "3. low": "91.7200",
            "4. close": "95.6200",
            "5. adjusted close": "93.8407",
            "6. volume": "45048781",
            "7. dividend amount": "0.2000"
        },
        "2021-07-30": {
            "1. open": "90.5200",
            "2. high": "96.5550",
            "3. low": "84.7900",
            "4. close": "95.4300",
            "5. adjusted close": "93.4558",
            "6. volume": "63949445",
            "7. dividend amount": "0.0000"
        },
        "2021-06-30": {
            "1. open": "96.6500",
            "2. high": "96.7800",
            "3. low": "86.7300",
            "4. close": "90.3700",
            "5. adjusted close": "88.5005",
            "6. volume": "74836864",
            "7. dividend amount": "0.0000"
        },
        "2021-05-28": {
            "1. open": "99.6180",
            "2. high": "106.8900",
            "3. low": "89.0350",
            "4. close": "95.2900",
            "5. adjusted close": "93.3187",
            "6. volume": "69447846",
            "7. dividend amount": "0.2000"
        },
        "2021-04-30": {
            "1. open": "90.0500",
            "2. high": "102.5950",
            "3. low": "89.3400",
            "4. close": "98.2900",
            "5. adjusted close": "96.0717",
            "6. volume": "63261851",
            "7. dividend amount": "0.0000"
        },
        "2021-03-31": {
            "1. open": "78.4100",
            "2. high": "91.0499",
            "3. low": "72.5700",
            "4. close": "89.1200",
            "5. adjusted close": "87.1086",
            "6. volume": "74373278",
            "7. dividend amount": "0.0000"
        },
        "2021-02-26": {
            "1. open": "77.4500",
            "2. high": "84.4100",
            "3. low": "74.1200",
            "4. close": "76.8700",
            "5. adjusted close": "75.1351",
            "6. volume": "56097047",
            "7. dividend amount": "0.2000"
        },
        "2021-01-29": {
            "1. open": "69.2400",
            "2. high": "83.2500",
            "3. low": "64.3200",
            "4. close": "76.8000",
            "5. adjusted close": "74.8770",
            "6. volume": "70293341",
            "7. dividend amount": "0.0000"
        },
        "2020-12-31": {
            "1. open": "74.6300",
            "2. high": "75.3000",
            "3. low": "68.8000",
            "4. close": "68.9200",
            "5. adjusted close": "67.1943",
            "6. volume": "60986750",
            "7. dividend amount": "0.2000"
        },
        "2020-11-30": {
            "1. open": "68.6600",
            "2. high": "78.2500",
            "3. low": "64.8200",
            "4. close": "74.5000",
            "5. adjusted close": "72.4343",
            "6. volume": "68106184",
            "7. dividend amount": "0.0000"
        },
        "2020-10-30": {
            "1. open": "76.7100",
            "2. high": "81.2100",
            "3. low": "66.1300",
            "4. close": "66.8100",
            "5. adjusted close": "64.9576",
            "6. volume": "56883276",
            "7. dividend amount": "0.0000"
        },
        "2020-09-30": {
            "1. open": "71.4700",
            "2. high": "76.6000",
            "3. low": "66.5100",
            "4. close": "75.6300",
            "5. adjusted close": "73.5330",
            "6. volume": "71819553",
            "7. dividend amount": "0.0000"
        },
        "2020-08-31": {
            "1. open": "66.7000",
            "2. high": "77.4500",
            "3. low": "66.5400",
            "4. close": "71.3700",
            "5. adjusted close": "69.3911",
            "6. volume": "71239732",
            "7. dividend amount": "0.1750"
        },
        "2020-07-31": {
            "1. open": "55.5600",
            "2. high": "70.2900",
            "3. low": "53.5000",
            "4. close": "66.1600",
            "5. adjusted close": "64.1630",
            "6. volume": "83421429",
            "7. dividend amount": "0.0000"
        },
        "2020-06-30": {
            "1. open": "55.5200",
            "2. high": "59.2400",
            "3. low": "50.9300",
            "4. close": "55.4500",
            "5. adjusted close": "53.7762",
            "6. volume": "92587454",
            "7. dividend amount": "0.0000"
        },
        "2020-05-29": {
            "1. open": "45.8400",
            "2. high": "59.8400",
            "3. low": "43.8200",
            "4. close": "55.3000",
            "5. adjusted close": "53.6308",
            "6. volume": "86176133",
            "7. dividend amount": "0.1750"
        },
        "2020-04-30": {
            "1. open": "32.6100",
            "2. high": "49.1300",
            "3. low": "31.2000",
            "4. close": "47.2200",
            "5. adjusted close": "45.6336",
            "6. volume": "116914509",
            "7. dividend amount": "0.0000"
        },
        "2020-03-31": {
            "1. open": "53.8200",
            "2. high": "58.5900",
            "3. low": "25.5100",
            "4. close": "34.0000",
            "5. adjusted close": "32.8578",
            "6. volume": "157274005",
            "7. dividend amount": "0.0000"
        },
        "2020-02-28": {
            "1. open": "59.4000",
            "2. high": "62.5400",
            "3. low": "52.0500",
            "4. close": "53.2700",
            "5. adjusted close": "51.4804",
            "6. volume": "74317896",
            "7. dividend amount": "0.1750"
        },
        "2020-01-31": {
            "1. open": "52.9500",
            "2. high": "61.7700",
            "3. low": "52.1300",
            "4. close": "59.2000",
            "5. adjusted close": "57.0467",
            "6. volume": "88200214",
            "7. dividend amount": "0.0000"
        },
        "2019-12-31": {
            "1. open": "55.2800",
            "2. high": "56.1200",
            "3. low": "51.7100",
            "4. close": "52.7500",
            "5. adjusted close": "50.8313",
            "6. volume": "68617328",
            "7. dividend amount": "0.0000"
        },
        "2019-11-29": {
            "1. open": "52.5000",
            "2. high": "55.8000",
            "3. low": "50.2000",
            "4. close": "55.3500",
            "5. adjusted close": "53.3367",
            "6. volume": "106193643",
            "7. dividend amount": "0.1750"
        },
        "2019-10-31": {
            "1. open": "52.6100",
            "2. high": "54.4200",
            "3. low": "50.1500",
            "4. close": "52.3700",
            "5. adjusted close": "50.3062",
            "6. volume": "97210250",
            "7. dividend amount": "0.0000"
        },
        "2019-09-30": {
            "1. open": "49.1500",
            "2. high": "53.0600",
            "3. low": "48.4700",
            "4. close": "52.7100",
            "5. adjusted close": "50.6328",
            "6. volume": "87124752",
            "7. dividend amount": "0.0000"
        },
        "2019-08-30": {
            "1. open": "46.2100",
            "2. high": "50.6400",
            "3. low": "45.4100",
            "4. close": "49.4700",
            "5. adjusted close": "47.5205",
            "6. volume": "95380375",
            "7. dividend amount": "0.1500"
        },
        "2019-07-31": {
            "1. open": "43.7300",
            "2. high": "47.2600",
            "3. low": "42.9300",
            "4. close": "45.9300",
            "5. adjusted close": "43.9803",
            "6. volume": "75393327",
            "7. dividend amount": "0.0000"
        },
        "2019-06-28": {
            "1. open": "42.6900",
            "2. high": "46.4700",
            "3. low": "41.4100",
            "4. close": "43.1300",
            "5. adjusted close": "41.2991",
            "6. volume": "79050546",
            "7. dividend amount": "0.0000"
        },
        "2019-05-31": {
            "1. open": "44.6100",
            "2. high": "45.6300",
            "3. low": "42.3700",
            "4. close": "42.7600",
            "5. adjusted close": "40.9449",
            "6. volume": "78191245",
            "7. dividend amount": "0.1500"
        },
        "2019-04-30": {
            "1. open": "41.5700",
            "2. high": "47.0200",
            "3. low": "40.8900",
            "4. close": "44.3100",
            "5. adjusted close": "42.2833",
            "6. volume": "118008130",
            "7. dividend amount": "0.0000"
        },
        "2019-03-29": {
            "1. open": "39.1700",
            "2. high": "43.3600",
            "3. low": "37.8100",
            "4. close": "41.3800",
            "5. adjusted close": "39.4873",
            "6. volume": "122259144",
            "7. dividend amount": "0.0000"
        },
        "2019-02-28": {
            "1. open": "38.5500",
            "2. high": "41.4800",
            "3. low": "37.1600",
            "4. close": "38.8900",
            "5. adjusted close": "37.1112",
            "6. volume": "118611614",
            "7. dividend amount": "0.1500"
        },
        "2019-01-31": {
            "1. open": "34.1500",
            "2. high": "40.1300",
            "3. low": "34.0800",
            "4. close": "38.4500",
            "5. adjusted close": "36.5460",
            "6. volume": "158293428",
            "7. dividend amount": "0.0000"
        },
        "2018-12-31": {
            "1. open": "37.6600",
            "2. high": "38.1100",
            "3. low": "32.3900",
            "4. close": "34.6600",
            "5. adjusted close": "32.9437",
            "6. volume": "93251233",
            "7. dividend amount": "0.0000"
        },
        "2018-11-30": {
            "1. open": "36.0500",
            "2. high": "37.9300",
            "3. low": "32.5300",
            "4. close": "37.2200",
            "5. adjusted close": "35.3769",
            "6. volume": "134738886",
            "7. dividend amount": "0.1500"
        },
        "2018-10-31": {
            "1. open": "42.2600",
            "2. high": "42.9300",
            "3. low": "34.3700",
            "4. close": "35.9600",
            "5. adjusted close": "34.0367",
            "6. volume": "135525172",
            "7. dividend amount": "0.0000"
        },
        "2018-09-28": {
            "1. open": "44.4700",
            "2. high": "45.7200",
            "3. low": "41.5600",
            "4. close": "42.1800",
            "5. adjusted close": "39.9241",
            "6. volume": "66991352",
            "7. dividend amount": "0.0000"
        },
        "2018-08-31": {
            "1. open": "43.9500",
            "2. high": "46.9100",
            "3. low": "42.8200",
            "4. close": "44.5100",
            "5. adjusted close": "42.1295",
            "6. volume": "75240839",
            "7. dividend amount": "0.1250"
        },
        "2018-07-31": {
            "1. open": "40.7800",
            "2. high": "44.9200",
            "3. low": "38.5800",
            "4. close": "43.7000",
            "5. adjusted close": "41.2464",
            "6. volume": "104354774",
            "7. dividend amount": "0.0000"
        },
        "2018-06-29": {
            "1. open": "42.4400",
            "2. high": "45.0000",
            "3. low": "39.3300",
            "4. close": "41.0000",
            "5. adjusted close": "38.6980",
            "6. volume": "88346934",
            "7. dividend amount": "0.0000"
        },
        "2018-05-31": {
            "1. open": "44.0000",
            "2. high": "45.2900",
            "3. low": "39.9700",
            "4. close": "42.2100",
            "5. adjusted close": "39.8400",
            "6. volume": "93455404",
            "7. dividend amount": "0.1250"
        },
        "2018-04-30": {
            "1. open": "43.6200",
            "2. high": "47.0000",
            "3. low": "41.6600",
            "4. close": "44.1400",
            "5. adjusted close": "41.5433",
            "6. volume": "92104464",
            "7. dividend amount": "0.0000"
        },
        "2018-03-29": {
            "1. open": "42.1400",
            "2. high": "45.2000",
            "3. low": "41.3400",
            "4. close": "43.8400",
            "5. adjusted close": "41.2609",
            "6. volume": "83393320",
            "7. dividend amount": "0.0000"
        },
        "2018-02-28": {
            "1. open": "48.4600",
            "2. high": "49.2800",
            "3. low": "41.9000",
            "4. close": "41.9000",
            "5. adjusted close": "39.4351",
            "6. volume": "118790507",
            "7. dividend amount": "0.1250"
        },
        "2018-01-31": {
            "1. open": "51.3700",
            "2. high": "53.3200",
            "3. low": "47.1400",
            "4. close": "49.0500",
            "5. adjusted close": "46.0344",
            "6. volume": "95252123",
            "7. dividend amount": "0.0000"
        },
        "2017-12-29": {
            "1. open": "50.9500",
            "2. high": "51.8300",
            "3. low": "49.1700",
            "4. close": "51.0700",
            "5. adjusted close": "47.9302",
            "6. volume": "66802413",
            "7. dividend amount": "0.0000"
        },
        "2017-11-30": {
            "1. open": "44.4600",
            "2. high": "51.5300",
            "3. low": "43.1000",
            "4. close": "51.0000",
            "5. adjusted close": "47.8646",
            "6. volume": "97347629",
            "7. dividend amount": "0.1250"
        },
        "2017-10-31": {
            "1. open": "40.3700",
            "2. high": "44.5800",
            "3. low": "39.7000",
            "4. close": "44.2100",
            "5. adjusted close": "41.3906",
            "6. volume": "79016310",
            "7. dividend amount": "0.0000"
        },
        "2017-09-29": {
            "1. open": "36.2600",
            "2. high": "40.0100",
            "3. low": "35.2900",
            "4. close": "39.9300",
            "5. adjusted close": "37.3835",
            "6. volume": "95916510",
            "7. dividend amount": "0.0000"
        },
        "2017-08-31": {
            "1. open": "35.7600",
            "2. high": "36.9900",
            "3. low": "34.9500",
            "4. close": "36.1500",
            "5. adjusted close": "33.8446",
            "6. volume": "67733050",
            "7. dividend amount": "0.1000"
        },
        "2017-07-31": {
            "1. open": "34.9000",
            "2. high": "37.4400",
            "3. low": "34.0600",
            "4. close": "35.6900",
            "5. adjusted close": "33.3224",
            "6. volume": "89356302",
            "7. dividend amount": "0.0000"
        },
        "2017-06-30": {
            "1. open": "32.7600",
            "2. high": "34.9399",
            "3. low": "32.5350",
            "4. close": "34.5700",
            "5. adjusted close": "32.2767",
            "6. volume": "81717560",
            "7. dividend amount": "0.0000"
        },
        "2017-05-31": {
            "1. open": "33.0100",
            "2. high": "34.3900",
            "3. low": "32.1900",
            "4. close": "32.6900",
            "5. adjusted close": "30.5214",
            "6. volume": "64402647",
            "7. dividend amount": "0.1000"
        },
        "2017-04-28": {
            "1. open": "33.3900",
            "2. high": "34.5400",
            "3. low": "31.9800",
            "4. close": "32.8900",
            "5. adjusted close": "30.6136",
            "6. volume": "80815322",
            "7. dividend amount": "0.0000"
        },
        "2017-03-31": {
            "1. open": "32.2300",
            "2. high": "34.0550",
            "3. low": "31.9100",
            "4. close": "33.3100",
            "5. adjusted close": "31.0045",
            "6. volume": "87810243",
            "7. dividend amount": "0.0000"
        },
        "2017-02-28": {
            "1. open": "30.0000",
            "2. high": "32.1700",
            "3. low": "29.2900",
            "4. close": "32.0000",
            "5. adjusted close": "29.7852",
            "6. volume": "79514356",
            "7. dividend amount": "0.1000"
        },
        "2017-01-31": {
            "1. open": "27.7100",
            "2. high": "31.9000",
            "3. low": "27.2100",
            "4. close": "29.9100",
            "5. adjusted close": "27.7464",
            "6. volume": "104729647",
            "7. dividend amount": "0.0000"
        },
        "2016-12-30": {
            "1. open": "27.7300",
            "2. high": "29.6950",
            "3. low": "27.1450",
            "4. close": "27.3300",
            "5. adjusted close": "25.3530",
            "6. volume": "92638617",
            "7. dividend amount": "0.0000"
        },
        "2016-11-30": {
            "1. open": "28.8300",
            "2. high": "29.4400",
            "3. low": "26.6900",
            "4. close": "27.7200",
            "5. adjusted close": "25.7148",
            "6. volume": "114428256",
            "7. dividend amount": "0.1000"
        },
        "2016-10-31": {
            "1. open": "30.0600",
            "2. high": "30.6200",
            "3. low": "27.7800",
            "4. close": "28.8300",
            "5. adjusted close": "26.6520",
            "6. volume": "77513913",
            "7. dividend amount": "0.0000"
        },
        "2016-09-30": {
            "1. open": "32.1100",
            "2. high": "32.2200",
            "3. low": "29.6350",
            "4. close": "30.2000",
            "5. adjusted close": "27.9185",
            "6. volume": "85660927",
            "7. dividend amount": "0.0000"
        },
        "2016-08-31": {
            "1. open": "32.8200",
            "2. high": "33.2600",
            "3. low": "31.6400",
            "4. close": "32.0600",
            "5. adjusted close": "29.6380",
            "6. volume": "71951474",
            "7. dividend amount": "0.0800"
        },
        "2016-07-29": {
            "1. open": "31.4800",
            "2. high": "34.5600",
            "3. low": "31.2701",
            "4. close": "32.8800",
            "5. adjusted close": "30.3204",
            "6. volume": "87303531",
            "7. dividend amount": "0.0000"
        },
        "2016-06-30": {
            "1. open": "30.3400",
            "2. high": "32.1000",
            "3. low": "29.1400",
            "4. close": "31.4800",
            "5. adjusted close": "29.0294",
            "6. volume": "69490993",
            "7. dividend amount": "0.0000"
        },
        "2016-05-31": {
            "1. open": "30.2800",
            "2. high": "30.9300",
            "3. low": "28.8200",
            "4. close": "30.5600",
            "5. adjusted close": "28.1810",
            "6. volume": "67453793",
            "7. dividend amount": "0.0800"
        },
        "2016-04-29": {
            "1. open": "30.0400",
            "2. high": "32.5100",
            "3. low": "29.4500",
            "4. close": "30.0600",
            "5. adjusted close": "27.6440",
            "6. volume": "74545281",
            "7. dividend amount": "0.0000"
        },
        "2016-03-31": {
            "1. open": "26.9900",
            "2. high": "31.0000",
            "3. low": "26.9000",
            "4. close": "30.2300",
            "5. adjusted close": "27.8003",
            "6. volume": "95654378",
            "7. dividend amount": "0.0000"
        },
        "2016-02-29": {
            "1. open": "27.3300",
            "2. high": "27.6800",
            "3. low": "22.9700",
            "4. close": "26.7200",
            "5. adjusted close": "24.5724",
            "6. volume": "122629294",
            "7. dividend amount": "0.0800"
        },
        "2016-01-29": {
            "1. open": "31.6000",
            "2. high": "31.6400",
            "3. low": "25.4100",
            "4. close": "27.5100",
            "5. adjusted close": "25.2205",
            "6. volume": "159016139",
            "7. dividend amount": "0.0000"
        },
        "2015-12-31": {
            "1. open": "32.4300",
            "2. high": "33.1000",
            "3. low": "30.6300",
            "4. close": "32.0300",
            "5. adjusted close": "29.3643",
            "6. volume": "77261192",
            "7. dividend amount": "0.0000"
        },
        "2015-11-30": {
            "1. open": "29.4300",
            "2. high": "32.9500",
            "3. low": "28.4500",
            "4. close": "32.3100",
            "5. adjusted close": "29.6210",
            "6. volume": "108461983",
            "7. dividend amount": "0.0800"
        },
        "2015-10-30": {
            "1. open": "29.4300",
            "2. high": "31.4750",
            "3. low": "28.5400",
            "4. close": "29.4400",
            "5. adjusted close": "26.9241",
            "6. volume": "129070855",
            "7. dividend amount": "0.0000"
        },
        "2015-09-30": {
            "1. open": "29.6800",
            "2. high": "33.0600",
            "3. low": "28.5800",
            "4. close": "29.3600",
            "5. adjusted close": "26.8509",
            "6. volume": "127123359",
            "7. dividend amount": "0.0000"
        },
        "2015-08-31": {
            "1. open": "29.6900",
            "2. high": "32.3700",
            "3. low": "27.6500",
            "4. close": "30.3700",
            "5. adjusted close": "27.7746",
            "6. volume": "130532636",
            "7. dividend amount": "0.0625"
        },
        "2015-07-31": {
            "1. open": "27.7200",
            "2. high": "29.8000",
            "3. low": "26.1400",
            "4. close": "29.6900",
            "5. adjusted close": "27.0937",
            "6. volume": "114696144",
            "7. dividend amount": "0.0000"
        },
        "2015-06-30": {
            "1. open": "26.2800",
            "2. high": "28.7000",
            "3. low": "25.6000",
            "4. close": "27.3600",
            "5. adjusted close": "24.9675",
            "6. volume": "85522682",
            "7. dividend amount": "0.0000"
        },
        "2015-05-29": {
            "1. open": "25.5300",
            "2. high": "27.4700",
            "3. low": "24.9150",
            "4. close": "26.1200",
            "5. adjusted close": "23.8359",
            "6. volume": "86818059",
            "7. dividend amount": "0.0625"
        },
        "2015-04-30": {
            "1. open": "28.6000",
            "2. high": "29.2900",
            "3. low": "25.3400",
            "4. close": "25.4000",
            "5. adjusted close": "23.1217",
            "6. volume": "124969239",
            "7. dividend amount": "0.0000"
        },
        "2015-03-31": {
            "1. open": "27.3500",
            "2. high": "28.7700",
            "3. low": "25.7700",
            "4. close": "28.4800",
            "5. adjusted close": "25.9254",
            "6. volume": "86158596",
            "7. dividend amount": "0.0000"
        },
        "2015-02-27": {
            "1. open": "24.6600",
            "2. high": "27.8400",
            "3. low": "24.3800",
            "4. close": "27.3100",
            "5. adjusted close": "24.8604",
            "6. volume": "108051159",
            "7. dividend amount": "0.0625"
        },
        "2015-01-30": {
            "1. open": "25.4800",
            "2. high": "26.8200",
            "3. low": "22.1199",
            "4. close": "24.5200",
            "5. adjusted close": "22.2669",
            "6. volume": "181190553",
            "7. dividend amount": "0.0000"
        },
        "2014-12-31": {
            "1. open": "25.4900",
            "2. high": "25.6200",
            "3. low": "23.3500",
            "4. close": "25.2900",
            "5. adjusted close": "22.9662",
            "6. volume": "103446344",
            "7. dividend amount": "0.0000"
        },
        "2014-11-28": {
            "1. open": "22.7900",
            "2. high": "25.9400",
            "3. low": "22.3200",
            "4. close": "25.4900",
            "5. adjusted close": "23.1478",
            "6. volume": "106153980",
            "7. dividend amount": "0.0625"
        },
        "2014-10-31": {
            "1. open": "20.5100",
            "2. high": "23.3100",
            "3. low": "19.2900",
            "4. close": "22.7900",
            "5. adjusted close": "20.6450",
            "6. volume": "148483850",
            "7. dividend amount": "0.0000"
        },
        "2014-09-30": {
            "1. open": "21.6700",
            "2. high": "22.4900",
            "3. low": "20.4000",
            "4. close": "20.5200",
            "5. adjusted close": "18.5887",
            "6. volume": "111034987",
            "7. dividend amount": "0.0000"
        },
        "2014-08-29": {
            "1. open": "20.6800",
            "2. high": "22.0700",
            "3. low": "19.9900",
            "4. close": "21.6800",
            "5. adjusted close": "19.6395",
            "6. volume": "116600100",
            "7. dividend amount": "0.0625"
        },
        "2014-07-31": {
            "1. open": "24.5700",
            "2. high": "25.2300",
            "3. low": "20.4700",
            "4. close": "20.7000",
            "5. adjusted close": "18.6938",
            "6. volume": "143113774",
            "7. dividend amount": "0.0000"
        },
        "2014-06-30": {
            "1. open": "23.6900",
            "2. high": "24.8300",
            "3. low": "22.8700",
            "4. close": "24.5800",
            "5. adjusted close": "22.1977",
            "6. volume": "91361900",
            "7. dividend amount": "0.0000"
        },
        "2014-05-30": {
            "1. open": "22.3500",
            "2. high": "24.0475",
            "3. low": "21.4700",
            "4. close": "23.6800",
            "5. adjusted close": "21.3850",
            "6. volume": "133237500",
            "7. dividend amount": "0.0375"
        },
        "2014-04-30": {
            "1. open": "21.7200",
            "2. high": "23.3500",
            "3. low": "21.0600",
            "4. close": "22.2800",
            "5. adjusted close": "20.0880",
            "6. volume": "135437900",
            "7. dividend amount": "0.0000"
        },
        "2014-03-31": {
            "1. open": "23.7900",
            "2. high": "24.7399",
            "3. low": "20.9500",
            "4. close": "21.6500",
            "5. adjusted close": "19.5200",
            "6. volume": "144120600",
            "7. dividend amount": "0.0000"
        },
        "2014-02-28": {
            "1. open": "23.4900",
            "2. high": "25.0600",
            "3. low": "22.5400",
            "4. close": "24.5600",
            "5. adjusted close": "22.1437",
            "6. volume": "136431000",
            "7. dividend amount": "0.0375"
        },
        "2014-01-31": {
            "1. open": "21.8100",
            "2. high": "24.0000",
            "3. low": "20.2000",
            "4. close": "23.4800",
            "5. adjusted close": "21.1350",
            "6. volume": "144593071",
            "7. dividend amount": "0.0000"
        },
        "2013-12-31": {
            "1. open": "19.8200",
            "2. high": "22.3500",
            "3. low": "18.6800",
            "4. close": "22.3200",
            "5. adjusted close": "20.0908",
            "6. volume": "135934600",
            "7. dividend amount": "0.0000"
        },
        "2013-11-29": {
            "1. open": "18.9900",
            "2. high": "20.4300",
            "3. low": "17.6700",
            "4. close": "19.8800",
            "5. adjusted close": "17.8945",
            "6. volume": "188461200",
            "7. dividend amount": "0.0000"
        },
        "2013-10-31": {
            "1. open": "19.4700",
            "2. high": "20.2300",
            "3. low": "17.5950",
            "4. close": "18.9500",
            "5. adjusted close": "17.0574",
            "6. volume": "166065700",
            "7. dividend amount": "0.0000"
        },
        "2013-09-30": {
            "1. open": "17.9100",
            "2. high": "21.6000",
            "3. low": "17.5200",
            "4. close": "19.4300",
            "5. adjusted close": "17.4895",
            "6. volume": "148257900",
            "7. dividend amount": "0.0000"
        },
        "2013-08-30": {
            "1. open": "20.3600",
            "2. high": "20.7600",
            "3. low": "17.5750",
            "4. close": "17.8500",
            "5. adjusted close": "16.0673",
            "6. volume": "169168600",
            "7. dividend amount": "0.0000"
        },
        "2013-07-31": {
            "1. open": "21.3800",
            "2. high": "23.2000",
            "3. low": "19.1300",
            "4. close": "20.1000",
            "5. adjusted close": "18.0926",
            "6. volume": "163153313",
            "7. dividend amount": "0.0000"
        },
        "2013-06-28": {
            "1. open": "24.4000",
            "2. high": "24.6500",
            "3. low": "19.9400",
            "4. close": "21.2800",
            "5. adjusted close": "19.1547",
            "6. volume": "177520300",
            "7. dividend amount": "0.0000"
        },
        "2013-05-31": {
            "1. open": "25.9700",
            "2. high": "27.7450",
            "3. low": "24.3100",
            "4. close": "24.3600",
            "5. adjusted close": "21.9271",
            "6. volume": "116054600",
            "7. dividend amount": "0.0000"
        },
        "2013-04-30": {
            "1. open": "24.3200",
            "2. high": "27.3200",
            "3. low": "21.2400",
            "4. close": "26.0800",
            "5. adjusted close": "23.4753",
            "6. volume": "137489200",
            "7. dividend amount": "0.0000"
        },
        "2013-03-28": {
            "1. open": "22.1400",
            "2. high": "25.5600",
            "3. low": "21.7500",
            "4. close": "24.3000",
            "5. adjusted close": "21.8731",
            "6. volume": "105754500",
            "7. dividend amount": "0.0000"
        },
        "2013-02-28": {
            "1. open": "23.8600",
            "2. high": "24.6600",
            "3. low": "21.3500",
            "4. close": "22.3000",
            "5. adjusted close": "20.0728",
            "6. volume": "116689900",
            "7. dividend amount": "0.0375"
        },
        "2013-01-31": {
            "1. open": "20.3400",
            "2. high": "24.0300",
            "3. low": "20.0200",
            "4. close": "23.6600",
            "5. adjusted close": "21.2634",
            "6. volume": "130872900",
            "7. dividend amount": "0.0000"
        },
        "2012-12-31": {
            "1. open": "19.5600",
            "2. high": "20.3000",
            "3. low": "18.2700",
            "4. close": "19.7800",
            "5. adjusted close": "17.7764",
            "6. volume": "105131400",
            "7. dividend amount": "0.1500"
        },
        "2012-11-30": {
            "1. open": "21.1000",
            "2. high": "22.3000",
            "3. low": "17.7100",
            "4. close": "19.4600",
            "5. adjusted close": "17.3510",
            "6. volume": "138021300",
            "7. dividend amount": "0.0375"
        },
        "2012-10-31": {
            "1. open": "20.8000",
            "2. high": "22.3200",
            "3. low": "19.7300",
            "4. close": "20.9600",
            "5. adjusted close": "18.6527",
            "6. volume": "120657800",
            "7. dividend amount": "0.0000"
        },
        "2012-09-28": {
            "1. open": "19.0000",
            "2. high": "22.7900",
            "3. low": "18.9150",
            "4. close": "20.6250",
            "5. adjusted close": "18.3546",
            "6. volume": "146592300",
            "7. dividend amount": "0.0000"
        },
        "2012-08-31": {
            "1. open": "17.6300",
            "2. high": "19.2200",
            "3. low": "16.9300",
            "4. close": "18.9900",
            "5. adjusted close": "16.8996",
            "6. volume": "128224900",
            "7. dividend amount": "0.0375"
        },
        "2012-07-31": {
            "1. open": "18.4500",
            "2. high": "19.3500",
            "3. low": "17.5100",
            "4. close": "17.6300",
            "5. adjusted close": "15.6576",
            "6. volume": "165796200",
            "7. dividend amount": "0.0000"
        },
        "2012-06-29": {
            "1. open": "16.2100",
            "2. high": "18.4500",
            "3. low": "14.3700",
            "4. close": "18.3800",
            "5. adjusted close": "16.3236",
            "6. volume": "168618600",
            "7. dividend amount": "0.0000"
        },
        "2012-05-31": {
            "1. open": "16.3000",
            "2. high": "17.9100",
            "3. low": "15.6300",
            "4. close": "16.6000",
            "5. adjusted close": "14.7428",
            "6. volume": "186427100",
            "7. dividend amount": "0.0375"
        },
        "2012-04-30": {
            "1. open": "15.1000",
            "2. high": "16.6900",
            "3. low": "13.8000",
            "4. close": "16.3500",
            "5. adjusted close": "14.4880",
            "6. volume": "192635774",
            "7. dividend amount": "0.0000"
        },
        "2012-03-30": {
            "1. open": "14.4400",
            "2. high": "16.4500",
            "3. low": "13.4500",
            "4. close": "15.1700",
            "5. adjusted close": "13.4424",
            "6. volume": "179331700",
            "7. dividend amount": "0.0000"
        },
        "2012-02-29": {
            "1. open": "13.9900",
            "2. high": "14.7900",
            "3. low": "13.7700",
            "4. close": "14.3400",
            "5. adjusted close": "12.7069",
            "6. volume": "137915000",
            "7. dividend amount": "0.0375"
        },
        "2012-01-31": {
            "1. open": "12.8900",
            "2. high": "14.7200",
            "3. low": "12.7400",
            "4. close": "13.9200",
            "5. adjusted close": "12.3029",
            "6. volume": "174920100",
            "7. dividend amount": "0.0000"
        },
        "2011-12-30": {
            "1. open": "11.9000",
            "2. high": "12.8900",
            "3. low": "11.6500",
            "4. close": "12.6100",
            "5. adjusted close": "11.1451",
            "6. volume": "137469100",
            "7. dividend amount": "0.0000"
        },
        "2011-11-30": {
            "1. open": "10.8100",
            "2. high": "12.0700",
            "3. low": "10.7400",
            "4. close": "11.9100",
            "5. adjusted close": "10.5264",
            "6. volume": "148101600",
            "7. dividend amount": "0.0750"
        },
        "2011-10-31": {
            "1. open": "9.0200",
            "2. high": "12.0000",
            "3. low": "8.0300",
            "4. close": "11.1300",
            "5. adjusted close": "9.7757",
            "6. volume": "161968400",
            "7. dividend amount": "0.0000"
        },
        "2011-09-30": {
            "1. open": "10.5500",
            "2. high": "10.6200",
            "3. low": "8.9677",
            "4. close": "9.0400",
            "5. adjusted close": "7.9400",
            "6. volume": "137379200",
            "7. dividend amount": "0.0000"
        },
        "2011-08-31": {
            "1. open": "12.0400",
            "2. high": "12.1200",
            "3. low": "8.8200",
            "4. close": "10.5200",
            "5. adjusted close": "9.2399",
            "6. volume": "199491700",
            "7. dividend amount": "0.0375"
        },
        "2011-07-29": {
            "1. open": "11.5700",
            "2. high": "12.5500",
            "3. low": "11.1600",
            "4. close": "11.8800",
            "5. adjusted close": "10.3920",
            "6. volume": "104282900",
            "7. dividend amount": "0.0000"
        },
        "2011-06-30": {
            "1. open": "12.1700",
            "2. high": "12.3400",
            "3. low": "10.6200",
            "4. close": "11.5200",
            "5. adjusted close": "10.0771",
            "6. volume": "121272700",
            "7. dividend amount": "0.0000"
        },
        "2011-05-31": {
            "1. open": "12.5500",
            "2. high": "12.5600",
            "3. low": "11.3800",
            "4. close": "12.1800",
            "5. adjusted close": "10.6544",
            "6. volume": "95224500",
            "7. dividend amount": "0.0375"
        },
        "2011-04-29": {
            "1. open": "11.7500",
            "2. high": "12.6800",
            "3. low": "11.0890",
            "4. close": "12.4400",
            "5. adjusted close": "10.8476",
            "6. volume": "100016000",
            "7. dividend amount": "0.0000"
        },
        "2011-03-31": {
            "1. open": "11.9300",
            "2. high": "12.3000",
            "3. low": "11.1850",
            "4. close": "11.6500",
            "5. adjusted close": "10.1587",
            "6. volume": "115545000",
            "7. dividend amount": "0.0000"
        },
        "2011-02-28": {
            "1. open": "12.4800",
            "2. high": "12.8900",
            "3. low": "11.5600",
            "4. close": "11.8400",
            "5. adjusted close": "10.3244",
            "6. volume": "98324500",
            "7. dividend amount": "0.0375"
        },
        "2011-01-31": {
            "1. open": "12.0600",
            "2. high": "13.5000",
            "3. low": "11.9300",
            "4. close": "12.3900",
            "5. adjusted close": "10.7714",
            "6. volume": "128952600",
            "7. dividend amount": "0.0000"
        },
        "2010-12-31": {
            "1. open": "10.1800",
            "2. high": "12.3000",
            "3. low": "10.0700",
            "4. close": "11.9300",
            "5. adjusted close": "10.3715",
            "6. volume": "128859300",
            "7. dividend amount": "0.0000"
        },
        "2010-11-30": {
            "1. open": "10.4700",
            "2. high": "12.2600",
            "3. low": "9.7700",
            "4. close": "10.0400",
            "5. adjusted close": "8.7284",
            "6. volume": "144207800",
            "7. dividend amount": "0.0375"
        },
        "2010-10-29": {
            "1. open": "11.2700",
            "2. high": "11.3400",
            "3. low": "10.0500",
            "4. close": "10.4300",
            "5. adjusted close": "9.0349",
            "6. volume": "111585000",
            "7. dividend amount": "0.0000"
        },
        "2010-09-30": {
            "1. open": "10.4600",
            "2. high": "11.3400",
            "3. low": "10.4300",
            "4. close": "11.1200",
            "5. adjusted close": "9.6326",
            "6. volume": "96978600",
            "7. dividend amount": "0.0000"
        },
        "2010-08-31": {
            "1. open": "11.2200",
            "2. high": "11.3800",
            "3. low": "9.7300",
            "4. close": "10.2600",
            "5. adjusted close": "8.8876",
            "6. volume": "124709500",
            "7. dividend amount": "0.0375"
        },
        "2010-07-30": {
            "1. open": "9.7800",
            "2. high": "11.3800",
            "3. low": "9.4100",
            "4. close": "11.0200",
            "5. adjusted close": "9.5110",
            "6. volume": "165199300",
            "7. dividend amount": "0.0000"
        },
        "2010-06-30": {
            "1. open": "12.1000",
            "2. high": "12.2900",
            "3. low": "9.8200",
            "4. close": "9.8300",
            "5. adjusted close": "8.4840",
            "6. volume": "184978100",
            "7. dividend amount": "0.0000"
        },
        "2010-05-28": {
            "1. open": "14.7100",
            "2. high": "15.2000",
            "3. low": "11.5700",
            "4. close": "12.1900",
            "5. adjusted close": "10.5208",
            "6. volume": "169210300",
            "7. dividend amount": "0.0375"
        },
        "2010-04-30": {
            "1. open": "12.7200",
            "2. high": "15.4400",
            "3. low": "11.7500",
            "4. close": "14.6900",
            "5. adjusted close": "12.6447",
            "6. volume": "160795700",
            "7. dividend amount": "0.0000"
        },
        "2010-03-31": {
            "1. open": "12.3700",
            "2. high": "13.4000",
            "3. low": "12.3100",
            "4. close": "12.6000",
            "5. adjusted close": "10.8457",
            "6. volume": "106765600",
            "7. dividend amount": "0.0000"
        },
        "2010-02-26": {
            "1. open": "11.8300",
            "2. high": "13.5300",
            "3. low": "11.6300",
            "4. close": "12.3600",
            "5. adjusted close": "10.6391",
            "6. volume": "177665000",
            "7. dividend amount": "0.0375"
        },
        "2010-01-29": {
            "1. open": "10.9600",
            "2. high": "12.6333",
            "3. low": "10.8700",
            "4. close": "11.7900",
            "5. adjusted close": "10.1196",
            "6. volume": "136318000",
            "7. dividend amount": "0.0000"
        },
        "2009-12-31": {
            "1. open": "10.4000",
            "2. high": "11.3300",
            "3. low": "9.6900",
            "4. close": "10.8700",
            "5. adjusted close": "9.3299",
            "6. volume": "146026800",
            "7. dividend amount": "0.0375"
        },
        "2009-11-30": {
            "1. open": "11.1100",
            "2. high": "12.5400",
            "3. low": "10.0500",
            "4. close": "10.2800",
            "5. adjusted close": "8.7907",
            "6. volume": "192606400",
            "7. dividend amount": "0.0000"
        },
        "2009-10-30": {
            "1. open": "11.2500",
            "2. high": "13.0000",
            "3. low": "10.4600",
            "4. close": "10.9600",
            "5. adjusted close": "9.3721",
            "6. volume": "195049500",
            "7. dividend amount": "0.0000"
        },
        "2009-09-30": {
            "1. open": "13.3100",
            "2. high": "13.8600",
            "3. low": "11.3000",
            "4. close": "11.4100",
            "5. adjusted close": "9.7570",
            "6. volume": "147500600",
            "7. dividend amount": "0.0000"
        },
        "2009-08-31": {
            "1. open": "11.7500",
            "2. high": "13.9000",
            "3. low": "11.0800",
            "4. close": "13.4100",
            "5. adjusted close": "11.4672",
            "6. volume": "196203800",
            "7. dividend amount": "0.0375"
        },
        "2009-07-31": {
            "1. open": "9.3200",
            "2. high": "11.7000",
            "3. low": "8.2600",
            "4. close": "11.5900",
            "5. adjusted close": "9.8797",
            "6. volume": "175778100",
            "7. dividend amount": "0.0000"
        },
        "2009-06-30": {
            "1. open": "9.3100",
            "2. high": "9.9100",
            "3. low": "9.0000",
            "4. close": "9.3600",
            "5. adjusted close": "7.9788",
            "6. volume": "191917100",
            "7. dividend amount": "0.0000"
        },
        "2009-05-29": {
            "1. open": "12.9900",
            "2. high": "13.6100",
            "3. low": "8.5400",
            "4. close": "9.2100",
            "5. adjusted close": "7.8509",
            "6. volume": "235561500",
            "7. dividend amount": "0.0375"
        },
        "2009-04-30": {
            "1. open": "9.3500",
            "2. high": "13.7400",
            "3. low": "9.2900",
            "4. close": "13.0500",
            "5. adjusted close": "11.0781",
            "6. volume": "215898700",
            "7. dividend amount": "0.0000"
        },
        "2009-03-31": {
            "1. open": "8.2100",
            "2. high": "11.3500",
            "3. low": "6.6200",
            "4. close": "9.7000",
            "5. adjusted close": "8.2343",
            "6. volume": "249038500",
            "7. dividend amount": "0.0000"
        },
        "2009-02-27": {
            "1. open": "5.9000",
            "2. high": "9.8100",
            "3. low": "5.7300",
            "4. close": "8.4500",
            "5. adjusted close": "7.1731",
            "6. volume": "277245200",
            "7. dividend amount": "0.0375"
        },
        "2009-01-30": {
            "1. open": "7.1000",
            "2. high": "8.3900",
            "3. low": "5.7200",
            "4. close": "5.9600",
            "5. adjusted close": "5.0372",
            "6. volume": "152765900",
            "7. dividend amount": "0.0000"
        },
        "2008-12-31": {
            "1. open": "6.6500",
            "2. high": "8.9500",
            "3. low": "5.9100",
            "4. close": "7.0700",
            "5. adjusted close": "5.9753",
            "6. volume": "158786300",
            "7. dividend amount": "0.0375"
        },
        "2008-11-28": {
            "1. open": "7.6300",
            "2. high": "8.1000",
            "3. low": "3.7900",
            "4. close": "6.8700",
            "5. adjusted close": "5.7785",
            "6. volume": "199392600",
            "7. dividend amount": "0.0000"
        },
        "2008-10-31": {
            "1. open": "12.5400",
            "2. high": "13.4000",
            "3. low": "4.3300",
            "4. close": "7.3800",
            "5. adjusted close": "6.2075",
            "6. volume": "313011800",
            "7. dividend amount": "0.0000"
        },
        "2008-09-30": {
            "1. open": "12.9100",
            "2. high": "15.4600",
            "3. low": "10.8900",
            "4. close": "13.0200",
            "5. adjusted close": "10.9515",
            "6. volume": "255877200",
            "7. dividend amount": "0.0000"
        },
        "2008-08-29": {
            "1. open": "11.1000",
            "2. high": "13.0200",
            "3. low": "10.4000",
            "4. close": "12.4600",
            "5. adjusted close": "10.4804",
            "6. volume": "149304100",
            "7. dividend amount": "0.0750"
        },
        "2008-07-31": {
            "1. open": "10.7400",
            "2. high": "13.2900",
            "3. low": "8.9300",
            "4. close": "11.1200",
            "5. adjusted close": "9.2932",
            "6. volume": "200307800",
            "7. dividend amount": "0.0000"
        },
        "2008-06-30": {
            "1. open": "12.6000",
            "2. high": "13.3600",
            "3. low": "10.7400",
            "4. close": "10.8500",
            "5. adjusted close": "9.0676",
            "6. volume": "177626500",
            "7. dividend amount": "0.0000"
        },
        "2008-05-30": {
            "1. open": "15.4500",
            "2. high": "16.9400",
            "3. low": "12.4500",
            "4. close": "12.7100",
            "5. adjusted close": "10.6220",
            "6. volume": "168931500",
            "7. dividend amount": "0.0750"
        },
        "2008-04-30": {
            "1. open": "16.0600",
            "2. high": "17.9500",
            "3. low": "14.9000",
            "4. close": "15.4900",
            "5. adjusted close": "12.8842",
            "6. volume": "174099400",
            "7. dividend amount": "0.0000"
        },
        "2008-03-31": {
            "1. open": "13.7500",
            "2. high": "17.4900",
            "3. low": "12.4300",
            "4. close": "15.7500",
            "5. adjusted close": "13.1004",
            "6. volume": "225741100",
            "7. dividend amount": "0.0000"
        },
        "2008-02-29": {
            "1. open": "17.2900",
            "2. high": "17.8000",
            "3. low": "13.4000",
            "4. close": "14.0300",
            "5. adjusted close": "11.6698",
            "6. volume": "218170600",
            "7. dividend amount": "0.1500"
        },
        "2008-01-31": {
            "1. open": "13.1900",
            "2. high": "17.8000",
            "3. low": "9.7800",
            "4. close": "17.2600",
            "5. adjusted close": "14.2060",
            "6. volume": "264879600",
            "7. dividend amount": "0.0000"
        },
        "2007-12-31": {
            "1. open": "11.7700",
            "2. high": "14.9000",
            "3. low": "11.6300",
            "4. close": "13.1700",
            "5. adjusted close": "10.8397",
            "6. volume": "142816700",
            "7. dividend amount": "0.0000"
        },
        "2007-11-30": {
            "1. open": "11.7500",
            "2. high": "13.2000",
            "3. low": "10.1500",
            "4. close": "11.9700",
            "5. adjusted close": "9.8520",
            "6. volume": "165549000",
            "7. dividend amount": "0.1500"
        },
        "2007-10-31": {
            "1. open": "13.1200",
            "2. high": "15.1800",
            "3. low": "11.6800",
            "4. close": "12.6900",
            "5. adjusted close": "10.3160",
            "6. volume": "188217600",
            "7. dividend amount": "0.0000"
        },
        "2007-09-28": {
            "1. open": "14.9600",
            "2. high": "16.6400",
            "3. low": "12.4600",
            "4. close": "12.8100",
            "5. adjusted close": "10.4136",
            "6. volume": "141627700",
            "7. dividend amount": "0.0000"
        },
        "2007-08-31": {
            "1. open": "16.2100",
            "2. high": "19.1000",
            "3. low": "14.4000",
            "4. close": "15.1100",
            "5. adjusted close": "12.2833",
            "6. volume": "214210500",
            "7. dividend amount": "0.1500"
        },
        "2007-07-31": {
            "1. open": "19.9300",
            "2. high": "20.7500",
            "3. low": "16.3100",
            "4. close": "16.3200",
            "5. adjusted close": "13.1413",
            "6. volume": "152957500",
            "7. dividend amount": "0.0000"
        },
        "2007-06-29": {
            "1. open": "23.4100",
            "2. high": "23.5700",
            "3. low": "19.7600",
            "4. close": "19.9300",
            "5. adjusted close": "16.0481",
            "6. volume": "86960800",
            "7. dividend amount": "0.0000"
        },
        "2007-05-31": {
            "1. open": "22.4900",
            "2. high": "24.4900",
            "3. low": "21.7500",
            "4. close": "23.3700",
            "5. adjusted close": "18.8181",
            "6. volume": "80505700",
            "7. dividend amount": "0.1500"
        },
        "2007-04-30": {
            "1. open": "22.1600",
            "2. high": "23.6000",
            "3. low": "21.0000",
            "4. close": "22.1800",
            "5. adjusted close": "17.7429",
            "6. volume": "113268000",
            "7. dividend amount": "0.0000"
        },
        "2007-03-30": {
            "1. open": "24.9200",
            "2. high": "25.8300",
            "3. low": "21.7900",
            "4. close": "22.0000",
            "5. adjusted close": "17.5989",
            "6. volume": "139634900",
            "7. dividend amount": "0.0000"
        },
        "2007-02-28": {
            "1. open": "29.2200",
            "2. high": "31.1300",
            "3. low": "25.0500",
            "4. close": "25.3600",
            "5. adjusted close": "20.2867",
            "6. volume": "78219100",
            "7. dividend amount": "0.0000"
        },
        "2007-01-31": {
            "1. open": "26.6000",
            "2. high": "29.3800",
            "3. low": "25.0500",
            "4. close": "29.0600",
            "5. adjusted close": "23.2465",
            "6. volume": "82706600",
            "7. dividend amount": "0.1500"
        },
        "2006-12-29": {
            "1. open": "26.6000",
            "2. high": "27.8100",
            "3. low": "25.7100",
            "4. close": "26.4900",
            "5. adjusted close": "21.0807",
            "6. volume": "64144700",
            "7. dividend amount": "0.0000"
        },
        "2006-11-30": {
            "1. open": "23.8000",
            "2. high": "27.0400",
            "3. low": "21.5100",
            "4. close": "26.6400",
            "5. adjusted close": "21.2000",
            "6. volume": "95111800",
            "7. dividend amount": "0.0000"
        },
        "2006-10-31": {
            "1. open": "23.7600",
            "2. high": "25.2400",
            "3. low": "22.7700",
            "4. close": "23.4300",
            "5. adjusted close": "18.6455",
            "6. volume": "70089700",
            "7. dividend amount": "0.1500"
        },
        "2006-09-29": {
            "1. open": "22.0500",
            "2. high": "25.4300",
            "3. low": "20.3700",
            "4. close": "23.9500",
            "5. adjusted close": "18.9384",
            "6. volume": "74904500",
            "7. dividend amount": "0.0000"
        },
        "2006-08-31": {
            "1. open": "21.0000",
            "2. high": "24.3500",
            "3. low": "19.9000",
            "4. close": "21.9300",
            "5. adjusted close": "17.3410",
            "6. volume": "83088400",
            "7. dividend amount": "0.1500"
        },
        "2006-07-31": {
            "1. open": "23.8200",
            "2. high": "24.4000",
            "3. low": "19.5200",
            "4. close": "21.4300",
            "5. adjusted close": "16.8299",
            "6. volume": "101150100",
            "7. dividend amount": "0.0000"
        },
        "2006-06-30": {
            "1. open": "26.3600",
            "2. high": "27.1800",
            "3. low": "22.5500",
            "4. close": "23.8200",
            "5. adjusted close": "18.7068",
            "6. volume": "101378800",
            "7. dividend amount": "0.0000"
        },
        "2006-05-31": {
            "1. open": "30.1090",
            "2. high": "30.5000",
            "3. low": "26.0900",
            "4. close": "26.3600",
            "5. adjusted close": "20.7016",
            "6. volume": "83046600",
            "7. dividend amount": "0.1000"
        },
        "2006-04-28": {
            "1. open": "33.1500",
            "2. high": "35.2700",
            "3. low": "29.8100",
            "4. close": "30.0200",
            "5. adjusted close": "23.4955",
            "6. volume": "53991000",
            "7. dividend amount": "0.0000"
        },
        "2006-03-31": {
            "1. open": "34.2500",
            "2. high": "34.9400",
            "3. low": "30.8000",
            "4. close": "33.2200",
            "5. adjusted close": "26.0001",
            "6. volume": "57571100",
            "7. dividend amount": "0.0000"
        },
        "2006-02-28": {
            "1. open": "37.1000",
            "2. high": "37.1900",
            "3. low": "31.9400",
            "4. close": "34.1100",
            "5. adjusted close": "26.6966",
            "6. volume": "52989700",
            "7. dividend amount": "0.0000"
        },
        "2006-01-31": {
            "1. open": "36.4600",
            "2. high": "41.6600",
            "3. low": "35.2000",
            "4. close": "37.3200",
            "5. adjusted close": "29.2090",
            "6. volume": "51289800",
            "7. dividend amount": "0.1000"
        },
        "2005-12-30": {
            "1. open": "35.9600",
            "2. high": "38.5600",
            "3. low": "34.2400",
            "4. close": "35.7300",
            "5. adjusted close": "27.8896",
            "6. volume": "37735900",
            "7. dividend amount": "0.0000"
        },
        "2005-11-30": {
            "1. open": "30.6100",
            "2. high": "37.4000",
            "3. low": "30.1000",
            "4. close": "35.4400",
            "5. adjusted close": "27.6632",
            "6. volume": "72605000",
            "7. dividend amount": "0.0000"
        },
        "2005-10-31": {
            "1. open": "36.3500",
            "2. high": "37.0500",
            "3. low": "28.7800",
            "4. close": "30.6900",
            "5. adjusted close": "23.9555",
            "6. volume": "74547000",
            "7. dividend amount": "0.0900"
        },
        "2005-09-30": {
            "1. open": "37.1500",
            "2. high": "38.9200",
            "3. low": "34.0600",
            "4. close": "36.2200",
            "5. adjusted close": "28.1884",
            "6. volume": "56451000",
            "7. dividend amount": "0.0000"
        },
        "2005-08-31": {
            "1. open": "41.3900",
            "2. high": "41.9900",
            "3. low": "33.3400",
            "4. close": "36.9200",
            "5. adjusted close": "28.7332",
            "6. volume": "74235900",
            "7. dividend amount": "0.0900"
        },
        "2005-07-29": {
            "1. open": "37.6400",
            "2. high": "42.8200",
            "3. low": "36.9400",
            "4. close": "41.0800",
            "5. adjusted close": "31.9004",
            "6. volume": "76308400",
            "7. dividend amount": "0.0000"
        },
        "2005-06-30": {
            "1. open": "34.5700",
            "2. high": "39.2000",
            "3. low": "33.6700",
            "4. close": "37.6100",
            "5. adjusted close": "29.2058",
            "6. volume": "52213500",
            "7. dividend amount": "0.0000"
        },
        "2005-05-31": {
            "1. open": "31.1000",
            "2. high": "34.9800",
            "3. low": "29.5600",
            "4. close": "34.5700",
            "5. adjusted close": "26.8451",
            "6. volume": "45749200",
            "7. dividend amount": "0.0900"
        },
        "2005-04-29": {
            "1. open": "30.5000",
            "2. high": "31.3700",
            "3. low": "26.8300",
            "4. close": "30.5000",
            "5. adjusted close": "23.6159",
            "6. volume": "61908000",
            "7. dividend amount": "0.0000"
        },
        "2005-03-31": {
            "1. open": "43.7700",
            "2. high": "46.1000",
            "3. low": "28.8200",
            "4. close": "29.2400",
            "5. adjusted close": "22.6403",
            "6. volume": "48465100",
            "7. dividend amount": "0.0000"
        },
        "2005-02-28": {
            "1. open": "39.9500",
            "2. high": "45.5500",
            "3. low": "39.8800",
            "4. close": "43.7600",
            "5. adjusted close": "25.4122",
            "6. volume": "43442175",
            "7. dividend amount": "0.0000"
        },
        "2005-01-31": {
            "1. open": "40.7500",
            "2. high": "41.9000",
            "3. low": "36.5800",
            "4. close": "39.7800",
            "5. adjusted close": "23.1010",
            "6. volume": "42274725",
            "7. dividend amount": "0.0900"
        },
        "2004-12-31": {
            "1. open": "35.9000",
            "2. high": "41.8800",
            "3. low": "35.1500",
            "4. close": "40.3100",
            "5. adjusted close": "23.3556",
            "6. volume": "37231350",
            "7. dividend amount": "0.0000"
        },
        "2004-11-30": {
            "1. open": "30.2500",
            "2. high": "36.6100",
            "3. low": "29.9400",
            "4. close": "35.2100",
            "5. adjusted close": "20.4007",
            "6. volume": "41439750",
            "7. dividend amount": "0.0000"
        },
        "2004-10-29": {
            "1. open": "33.6300",
            "2. high": "33.6300",
            "3. low": "27.2000",
            "4. close": "30.0000",
            "5. adjusted close": "17.3820",
            "6. volume": "50678625",
            "7. dividend amount": "0.0800"
        },
        "2004-09-30": {
            "1. open": "30.9400",
            "2. high": "34.3300",
            "3. low": "30.9400",
            "4. close": "33.1100",
            "5. adjusted close": "19.1285",
            "6. volume": "28170375",
            "7. dividend amount": "0.0000"
        },
        "2004-08-31": {
            "1. open": "27.2500",
            "2. high": "31.5000",
            "3. low": "27.2000",
            "4. close": "30.9400",
            "5. adjusted close": "17.8748",
            "6. volume": "28023450",
            "7. dividend amount": "0.0800"
        },
        "2004-07-30": {
            "1. open": "28.3900",
            "2. high": "29.0400",
            "3. low": "24.7700",
            "4. close": "27.6300",
            "5. adjusted close": "15.9180",
            "6. volume": "34585725",
            "7. dividend amount": "0.0000"
        },
        "2004-06-30": {
            "1. open": "28.9600",
            "2. high": "31.0200",
            "3. low": "27.4000",
            "4. close": "28.4000",
            "5. adjusted close": "16.3616",
            "6. volume": "35968050",
            "7. dividend amount": "0.0000"
        },
        "2004-05-28": {
            "1. open": "28.9500",
            "2. high": "29.7100",
            "3. low": "24.6300",
            "4. close": "28.9000",
            "5. adjusted close": "16.6497",
            "6. volume": "45648375",
            "7. dividend amount": "0.0800"
        },
        "2004-04-30": {
            "1. open": "35.9500",
            "2. high": "35.9500",
            "3. low": "28.2700",
            "4. close": "28.8000",
            "5. adjusted close": "16.5465",
            "6. volume": "48079050",
            "7. dividend amount": "0.0000"
        },
        "2004-03-31": {
            "1. open": "32.0000",
            "2. high": "36.5000",
            "3. low": "32.0000",
            "4. close": "35.4300",
            "5. adjusted close": "20.3556",
            "6. volume": "43167375",
            "7. dividend amount": "0.0000"
        },
        "2004-02-27": {
            "1. open": "28.1000",
            "2. high": "32.1000",
            "3. low": "27.6000",
            "4. close": "31.7900",
            "5. adjusted close": "18.2643",
            "6. volume": "34666275",
            "7. dividend amount": "0.0000"
        },
        "2004-01-30": {
            "1. open": "43.4500",
            "2. high": "43.6600",
            "3. low": "24.8300",
            "4. close": "28.1000",
            "5. adjusted close": "16.1443",
            "6. volume": "52148450",
            "7. dividend amount": "0.0800"
        },
        "2003-12-31": {
            "1. open": "44.3000",
            "2. high": "45.3700",
            "3. low": "38.6200",
            "4. close": "43.2600",
            "5. adjusted close": "16.5218",
            "6. volume": "34024050",
            "7. dividend amount": "0.0000"
        },
        "2003-11-28": {
            "1. open": "40.4000",
            "2. high": "44.1700",
            "3. low": "38.9000",
            "4. close": "43.7000",
            "5. adjusted close": "16.6899",
            "6. volume": "27502150",
            "7. dividend amount": "0.0000"
        },
        "2003-10-31": {
            "1. open": "32.7100",
            "2. high": "40.7500",
            "3. low": "32.5900",
            "4. close": "39.8000",
            "5. adjusted close": "15.2004",
            "6. volume": "31227950",
            "7. dividend amount": "0.0700"
        },
        "2003-09-30": {
            "1. open": "31.1200",
            "2. high": "33.2700",
            "3. low": "29.2500",
            "4. close": "32.7000",
            "5. adjusted close": "12.4656",
            "6. volume": "26535600",
            "7. dividend amount": "0.0000"
        },
        "2003-08-29": {
            "1. open": "28.0000",
            "2. high": "31.9700",
            "3. low": "26.8200",
            "4. close": "31.1200",
            "5. adjusted close": "11.8633",
            "6. volume": "24824850",
            "7. dividend amount": "0.0700"
        },
        "2003-07-31": {
            "1. open": "28.1100",
            "2. high": "30.8900",
            "3. low": "7.1700",
            "4. close": "28.1500",
            "5. adjusted close": "10.7043",
            "6. volume": "33352000",
            "7. dividend amount": "0.0000"
        },
        "2003-06-30": {
            "1. open": "26.6000",
            "2. high": "32.3000",
            "3. low": "20.2200",
            "4. close": "28.1000",
            "5. adjusted close": "10.6853",
            "6. volume": "39154750",
            "7. dividend amount": "0.0000"
        },
        "2003-05-30": {
            "1. open": "23.7600",
            "2. high": "26.9700",
            "3. low": "23.0900",
            "4. close": "26.2900",
            "5. adjusted close": "9.9970",
            "6. volume": "30801150",
            "7. dividend amount": "0.0700"
        },
        "2003-04-30": {
            "1. open": "19.3200",
            "2. high": "23.9800",
            "3. low": "18.9600",
            "4. close": "23.7000",
            "5. adjusted close": "8.9866",
            "6. volume": "20727950",
            "7. dividend amount": "0.0000"
        },
        "2003-03-31": {
            "1. open": "18.5000",
            "2. high": "20.2500",
            "3. low": "16.9500",
            "4. close": "19.2000",
            "5. adjusted close": "7.2803",
            "6. volume": "24050000",
            "7. dividend amount": "0.0000"
        },
        "2003-02-28": {
            "1. open": "19.2500",
            "2. high": "19.6800",
            "3. low": "17.9000",
            "4. close": "18.3100",
            "5. adjusted close": "6.9428",
            "6. volume": "16817500",
            "7. dividend amount": "0.0000"
        },
        "2003-01-31": {
            "1. open": "17.5500",
            "2. high": "20.4500",
            "3. low": "17.1400",
            "4. close": "19.1000",
            "5. adjusted close": "7.2424",
            "6. volume": "26896400",
            "7. dividend amount": "0.0700"
        },
        "2002-12-31": {
            "1. open": "19.2000",
            "2. high": "19.4500",
            "3. low": "16.8200",
            "4. close": "17.3500",
            "5. adjusted close": "6.5545",
            "6. volume": "20170250",
            "7. dividend amount": "0.0000"
        },
        "2002-11-29": {
            "1. open": "19.2200",
            "2. high": "20.3600",
            "3. low": "16.9500",
            "4. close": "19.1100",
            "5. adjusted close": "7.2194",
            "6. volume": "27917050",
            "7. dividend amount": "0.0000"
        },
        "2002-10-31": {
            "1. open": "18.7200",
            "2. high": "21.0100",
            "3. low": "16.0300",
            "4. close": "19.2700",
            "5. adjusted close": "7.2798",
            "6. volume": "25913500",
            "7. dividend amount": "0.0600"
        },
        "2002-09-30": {
            "1. open": "20.5400",
            "2. high": "22.5800",
            "3. low": "18.3000",
            "4. close": "18.6200",
            "5. adjusted close": "7.0124",
            "6. volume": "23477100",
            "7. dividend amount": "0.0000"
        },
        "2002-08-30": {
            "1. open": "22.0000",
            "2. high": "22.5900",
            "3. low": "18.6500",
            "4. close": "20.7600",
            "5. adjusted close": "7.8184",
            "6. volume": "26100400",
            "7. dividend amount": "0.0600"
        },
        "2002-07-31": {
            "1. open": "26.5000",
            "2. high": "26.8500",
            "3. low": "19.4000",
            "4. close": "22.2000",
            "5. adjusted close": "8.3359",
            "6. volume": "35179950",
            "7. dividend amount": "0.0000"
        },
        "2002-06-28": {
            "1. open": "24.6500",
            "2. high": "27.5000",
            "3. low": "21.8500",
            "4. close": "26.0300",
            "5. adjusted close": "9.7740",
            "6. volume": "32023050",
            "7. dividend amount": "0.0000"
        },
        "2002-05-31": {
            "1. open": "25.9500",
            "2. high": "27.1900",
            "3. low": "23.9900",
            "4. close": "24.5200",
            "5. adjusted close": "9.2070",
            "6. volume": "27340400",
            "7. dividend amount": "0.0600"
        },
        "2002-04-30": {
            "1. open": "37.2500",
            "2. high": "38.0800",
            "3. low": "23.0600",
            "4. close": "25.8000",
            "5. adjusted close": "9.6646",
            "6. volume": "42378700",
            "7. dividend amount": "0.0000"
        },
        "2002-03-28": {
            "1. open": "39.9100",
            "2. high": "43.7500",
            "3. low": "36.5000",
            "4. close": "37.7000",
            "5. adjusted close": "9.4149",
            "6. volume": "31946469",
            "7. dividend amount": "0.0000"
        },
        "2002-02-28": {
            "1. open": "37.4800",
            "2. high": "40.3800",
            "3. low": "35.2600",
            "4. close": "39.9000",
            "5. adjusted close": "9.9643",
            "6. volume": "28897368",
            "7. dividend amount": "0.0600"
        },
        "2002-01-31": {
            "1. open": "32.2100",
            "2. high": "37.8000",
            "3. low": "29.7500",
            "4. close": "37.4400",
            "5. adjusted close": "9.3347",
            "6. volume": "20513735",
            "7. dividend amount": "0.0000"
        },
        "2001-12-31": {
            "1. open": "28.9400",
            "2. high": "33.5000",
            "3. low": "27.6100",
            "4. close": "32.4600",
            "5. adjusted close": "8.0930",
            "6. volume": "18667635",
            "7. dividend amount": "0.0000"
        },
        "2001-11-30": {
            "1. open": "22.5000",
            "2. high": "28.5500",
            "3. low": "22.0200",
            "4. close": "28.0200",
            "5. adjusted close": "6.9861",
            "6. volume": "13082567",
            "7. dividend amount": "0.0000"
        },
        "2001-10-31": {
            "1. open": "20.6100",
            "2. high": "25.2400",
            "3. low": "19.8700",
            "4. close": "22.3500",
            "5. adjusted close": "5.5724",
            "6. volume": "14155803",
            "7. dividend amount": "0.0500"
        },
        "2001-09-28": {
            "1. open": "25.8000",
            "2. high": "26.3000",
            "3. low": "17.5000",
            "4. close": "20.8600",
            "5. adjusted close": "5.1903",
            "6. volume": "9509134",
            "7. dividend amount": "0.0000"
        },
        "2001-08-31": {
            "1. open": "28.0000",
            "2. high": "28.7500",
            "3. low": "22.2000",
            "4. close": "25.2400",
            "5. adjusted close": "6.2801",
            "6. volume": "14803236",
            "7. dividend amount": "0.0500"
        },
        "2001-07-31": {
            "1. open": "23.3000",
            "2. high": "30.0000",
            "3. low": "23.3000",
            "4. close": "27.5500",
            "5. adjusted close": "6.8412",
            "6. volume": "18429370",
            "7. dividend amount": "0.0000"
        },
        "2001-06-29": {
            "1. open": "20.7500",
            "2. high": "24.2500",
            "3. low": "20.4200",
            "4. close": "22.7000",
            "5. adjusted close": "5.6369",
            "6. volume": "11286234",
            "7. dividend amount": "0.0000"
        },
        "2001-05-31": {
            "1. open": "24.2500",
            "2. high": "24.7500",
            "3. low": "19.2500",
            "4. close": "20.6200",
            "5. adjusted close": "5.1204",
            "6. volume": "17784370",
            "7. dividend amount": "0.0500"
        },
        "2001-04-30": {
            "1. open": "20.6000",
            "2. high": "25.9900",
            "3. low": "19.7500",
            "4. close": "24.2200",
            "5. adjusted close": "6.0010",
            "6. volume": "11601402",
            "7. dividend amount": "0.0000"
        },
        "2001-03-30": {
            "1. open": "22.0000",
            "2. high": "23.4700",
            "3. low": "17.9000",
            "4. close": "21.1500",
            "5. adjusted close": "5.2403",
            "6. volume": "8872433",
            "7. dividend amount": "0.0000"
        },
        "2001-02-28": {
            "1. open": "22.7500",
            "2. high": "25.2500",
            "3. low": "20.5000",
            "4. close": "22.8000",
            "5. adjusted close": "5.0893",
            "6. volume": "8389533",
            "7. dividend amount": "0.0500"
        },
        "2001-01-31": {
            "1. open": "26.0000",
            "2. high": "27.0000",
            "3. low": "20.7500",
            "4. close": "23.5300",
            "5. adjusted close": "5.2413",
            "6. volume": "16616464",
            "7. dividend amount": "0.0000"
        },
        "2000-12-29": {
            "1. open": "18.6900",
            "2. high": "26.0000",
            "3. low": "18.3100",
            "4. close": "24.4400",
            "5. adjusted close": "5.4440",
            "6. volume": "13129138",
            "7. dividend amount": "0.0000"
        },
        "2000-11-30": {
            "1. open": "18.6900",
            "2. high": "20.0000",
            "3. low": "18.0000",
            "4. close": "18.5600",
            "5. adjusted close": "4.1342",
            "6. volume": "7405536",
            "7. dividend amount": "0.0000"
        },
        "2000-10-31": {
            "1. open": "17.5000",
            "2. high": "19.1300",
            "3. low": "15.2500",
            "4. close": "18.5000",
            "5. adjusted close": "4.1208",
            "6. volume": "7183901",
            "7. dividend amount": "0.0400"
        },
        "2000-09-29": {
            "1. open": "20.0000",
            "2. high": "21.0000",
            "3. low": "15.5600",
            "4. close": "17.1900",
            "5. adjusted close": "3.8195",
            "6. volume": "6953869",
            "7. dividend amount": "0.0000"
        },
        "2000-08-31": {
            "1. open": "15.5000",
            "2. high": "20.2500",
            "3. low": "15.3100",
            "4. close": "19.6300",
            "5. adjusted close": "4.3617",
            "6. volume": "6823068",
            "7. dividend amount": "0.0400"
        },
        "2000-07-31": {
            "1. open": "13.7500",
            "2. high": "15.8800",
            "3. low": "13.7500",
            "4. close": "15.5000",
            "5. adjusted close": "3.4367",
            "6. volume": "4527004",
            "7. dividend amount": "0.0000"
        },
        "2000-06-30": {
            "1. open": "13.0000",
            "2. high": "14.5000",
            "3. low": "13.0000",
            "4. close": "13.5600",
            "5. adjusted close": "3.0065",
            "6. volume": "4110301",
            "7. dividend amount": "0.0000"
        },
        "2000-05-31": {
            "1. open": "13.1900",
            "2. high": "14.6300",
            "3. low": "12.5600",
            "4. close": "13.1900",
            "5. adjusted close": "2.9245",
            "6. volume": "5358602",
            "7. dividend amount": "0.0330"
        },
        "2000-04-28": {
            "1. open": "12.9400",
            "2. high": "13.9400",
            "3. low": "12.1900",
            "4. close": "12.9400",
            "5. adjusted close": "2.8622",
            "6. volume": "5882534",
            "7. dividend amount": "0.0000"
        },
        "2000-03-31": {
            "1. open": "11.3800",
            "2. high": "14.0600",
            "3. low": "11.2500",
            "4. close": "13.0600",
            "5. adjusted close": "2.8888",
            "6. volume": "7871369",
            "7. dividend amount": "0.0000"
        },
        "2000-02-29": {
            "1. open": "11.6900",
            "2. high": "13.3100",
            "3. low": "11.1200",
            "4. close": "11.2500",
            "5. adjusted close": "2.4884",
            "6. volume": "7189931",
            "7. dividend amount": "0.0330"
        },
        "2000-01-31": {
            "1. open": "13.8100",
            "2. high": "13.8100",
            "3. low": "10.8800",
            "4. close": "11.6300",
            "5. adjusted close": "2.5655",
            "6. volume": "7893801",
            "7. dividend amount": "0.0000"
        },
        "1999-12-31": {
            "1. open": "13.8100",
            "2. high": "14.5600",
            "3. low": "11.7500",
            "4. close": "13.8100",
            "5. adjusted close": "3.0464",
            "6. volume": "6679837",
            "7. dividend amount": "0.0000"
        }
    }
}