{
    "Meta Data": {
        "1. Information": "Monthly Adjusted Prices and Volumes",
        "2. Symbol": "MS",
        "3. Last Refreshed": "2023-06-05",
        "4. Time Zone": "US/Eastern"
    },
    "Monthly Adjusted Time Series": {
        "2023-06-05": {
            "1. open": "82.5800",
            "2. high": "84.7295",
            "3. low": "81.4700",
            "4. close": "83.7400",
            "5. adjusted close": "83.7400",
            "6. volume": "19707809",
            "7. dividend amount": "0.0000"
        },
        "2023-05-31": {
            "1. open": "90.1900",
            "2. high": "90.5200",
            "3. low": "80.7400",
            "4. close": "81.7600",
            "5. adjusted close": "81.7600",
            "6. volume": "150282218",
            "7. dividend amount": "0.0000"
        },
        "2023-04-28": {
            "1. open": "87.9500",
            "2. high": "91.8200",
            "3. low": "83.2000",
            "4. close": "89.9700",
            "5. adjusted close": "89.9700",
            "6. volume": "129472888",
            "7. dividend amount": "0.7750"
        },
        "2023-03-31": {
            "1. open": "95.9600",
            "2. high": "99.2000",
            "3. low": "81.7200",
            "4. close": "87.8000",
            "5. adjusted close": "87.0502",
            "6. volume": "205268207",
            "7. dividend amount": "0.0000"
        },
        "2023-02-28": {
            "1. open": "96.9500",
            "2. high": "100.9900",
            "3. low": "96.2600",
            "4. close": "96.5000",
            "5. adjusted close": "95.6758",
            "6. volume": "121184137",
            "7. dividend amount": "0.0000"
        },
        "2023-01-31": {
            "1. open": "85.6350",
            "2. high": "99.1000",
            "3. low": "84.8300",
            "4. close": "97.3300",
            "5. adjusted close": "96.4988",
            "6. volume": "168742543",
            "7. dividend amount": "0.7750"
        },
        "2022-12-30": {
            "1. open": "93.0600",
            "2. high": "95.1600",
            "3. low": "84.0600",
            "4. close": "85.0200",
            "5. adjusted close": "83.6186",
            "6. volume": "145899195",
            "7. dividend amount": "0.0000"
        },
        "2022-11-30": {
            "1. open": "83.2500",
            "2. high": "93.2500",
            "3. low": "82.5500",
            "4. close": "93.0700",
            "5. adjusted close": "91.5359",
            "6. volume": "131120131",
            "7. dividend amount": "0.0000"
        },
        "2022-10-31": {
            "1. open": "80.0500",
            "2. high": "84.7400",
            "3. low": "74.6700",
            "4. close": "82.1700",
            "5. adjusted close": "80.8155",
            "6. volume": "171009909",
            "7. dividend amount": "0.7750"
        },
        "2022-09-30": {
            "1. open": "84.6700",
            "2. high": "91.0400",
            "3. low": "78.3500",
            "4. close": "79.0100",
            "5. adjusted close": "76.9820",
            "6. volume": "182787247",
            "7. dividend amount": "0.0000"
        },
        "2022-08-31": {
            "1. open": "83.6600",
            "2. high": "92.2900",
            "3. low": "82.9600",
            "4. close": "85.2200",
            "5. adjusted close": "83.0326",
            "6. volume": "152432564",
            "7. dividend amount": "0.0000"
        },
        "2022-07-29": {
            "1. open": "75.7600",
            "2. high": "84.6300",
            "3. low": "72.0500",
            "4. close": "84.3000",
            "5. adjusted close": "82.1362",
            "6. volume": "158632374",
            "7. dividend amount": "0.7750"
        },
        "2022-06-30": {
            "1. open": "86.4400",
            "2. high": "86.7800",
            "3. low": "72.2300",
            "4. close": "76.0600",
            "5. adjusted close": "73.4217",
            "6. volume": "174795389",
            "7. dividend amount": "0.0000"
        },
        "2022-05-31": {
            "1. open": "80.5900",
            "2. high": "87.5300",
            "3. low": "76.7500",
            "4. close": "86.1400",
            "5. adjusted close": "83.1521",
            "6. volume": "172235917",
            "7. dividend amount": "0.0000"
        },
        "2022-04-29": {
            "1. open": "88.1400",
            "2. high": "92.9300",
            "3. low": "80.3100",
            "4. close": "80.5900",
            "5. adjusted close": "77.7946",
            "6. volume": "196861591",
            "7. dividend amount": "0.7000"
        },
        "2022-03-31": {
            "1. open": "90.0000",
            "2. high": "94.9100",
            "3. low": "81.9700",
            "4. close": "87.4000",
            "5. adjusted close": "83.6662",
            "6. volume": "251910854",
            "7. dividend amount": "0.0000"
        },
        "2022-02-28": {
            "1. open": "102.9600",
            "2. high": "109.7300",
            "3. low": "88.5300",
            "4. close": "90.7400",
            "5. adjusted close": "86.8635",
            "6. volume": "202652193",
            "7. dividend amount": "0.0000"
        },
        "2022-01-31": {
            "1. open": "99.3300",
            "2. high": "106.4700",
            "3. low": "92.9400",
            "4. close": "102.5400",
            "5. adjusted close": "98.1594",
            "6. volume": "269672469",
            "7. dividend amount": "0.7000"
        },
        "2021-12-31": {
            "1. open": "96.9800",
            "2. high": "103.1600",
            "3. low": "94.2100",
            "4. close": "98.1600",
            "5. adjusted close": "93.3248",
            "6. volume": "190305547",
            "7. dividend amount": "0.0000"
        },
        "2021-11-30": {
            "1. open": "103.8900",
            "2. high": "105.3350",
            "3. low": "93.8800",
            "4. close": "94.8200",
            "5. adjusted close": "90.1493",
            "6. volume": "194107581",
            "7. dividend amount": "0.0000"
        },
        "2021-10-29": {
            "1. open": "97.9300",
            "2. high": "103.9800",
            "3. low": "96.6800",
            "4. close": "102.7800",
            "5. adjusted close": "97.7172",
            "6. volume": "166952426",
            "7. dividend amount": "0.7000"
        },
        "2021-09-30": {
            "1. open": "104.5400",
            "2. high": "105.9500",
            "3. low": "96.2500",
            "4. close": "97.3100",
            "5. adjusted close": "91.8891",
            "6. volume": "179632552",
            "7. dividend amount": "0.0000"
        },
        "2021-08-31": {
            "1. open": "96.7200",
            "2. high": "105.8100",
            "3. low": "94.8300",
            "4. close": "104.4300",
            "5. adjusted close": "98.6125",
            "6. volume": "159622597",
            "7. dividend amount": "0.0000"
        },
        "2021-07-30": {
            "1. open": "91.9200",
            "2. high": "97.2050",
            "3. low": "86.9500",
            "4. close": "95.9800",
            "5. adjusted close": "90.6332",
            "6. volume": "212917105",
            "7. dividend amount": "0.7000"
        },
        "2021-06-30": {
            "1. open": "92.3900",
            "2. high": "94.2700",
            "3. low": "83.9100",
            "4. close": "91.6900",
            "5. adjusted close": "85.9572",
            "6. volume": "206015210",
            "7. dividend amount": "0.0000"
        },
        "2021-05-28": {
            "1. open": "83.1100",
            "2. high": "91.3483",
            "3. low": "80.7500",
            "4. close": "90.9500",
            "5. adjusted close": "85.2635",
            "6. volume": "194947708",
            "7. dividend amount": "0.0000"
        },
        "2021-04-30": {
            "1. open": "77.8800",
            "2. high": "83.7900",
            "3. low": "76.2500",
            "4. close": "82.5500",
            "5. adjusted close": "77.3887",
            "6. volume": "229851900",
            "7. dividend amount": "0.3500"
        },
        "2021-03-31": {
            "1. open": "78.0500",
            "2. high": "86.6400",
            "3. low": "76.0000",
            "4. close": "77.6600",
            "5. adjusted close": "72.5010",
            "6. volume": "261537221",
            "7. dividend amount": "0.0000"
        },
        "2021-02-26": {
            "1. open": "67.8800",
            "2. high": "81.3950",
            "3. low": "67.2701",
            "4. close": "76.8700",
            "5. adjusted close": "71.7635",
            "6. volume": "198251468",
            "7. dividend amount": "0.0000"
        },
        "2021-01-29": {
            "1. open": "69.2800",
            "2. high": "77.7600",
            "3. low": "66.8450",
            "4. close": "67.0500",
            "5. adjusted close": "62.5959",
            "6. volume": "259829839",
            "7. dividend amount": "0.3500"
        },
        "2020-12-31": {
            "1. open": "63.1200",
            "2. high": "68.9700",
            "3. low": "61.8600",
            "4. close": "68.5300",
            "5. adjusted close": "63.6561",
            "6. volume": "203108634",
            "7. dividend amount": "0.0000"
        },
        "2020-11-30": {
            "1. open": "48.8750",
            "2. high": "63.9600",
            "3. low": "48.4400",
            "4. close": "61.8300",
            "5. adjusted close": "57.4327",
            "6. volume": "247897578",
            "7. dividend amount": "0.0000"
        },
        "2020-10-30": {
            "1. open": "48.7500",
            "2. high": "52.6100",
            "3. low": "46.4200",
            "4. close": "48.1500",
            "5. adjusted close": "44.7256",
            "6. volume": "354556673",
            "7. dividend amount": "0.3500"
        },
        "2020-09-30": {
            "1. open": "51.9200",
            "2. high": "54.3800",
            "3. low": "45.8600",
            "4. close": "48.3500",
            "5. adjusted close": "44.5870",
            "6. volume": "202187783",
            "7. dividend amount": "0.0000"
        },
        "2020-08-31": {
            "1. open": "49.2200",
            "2. high": "53.4200",
            "3. low": "48.7200",
            "4. close": "52.2600",
            "5. adjusted close": "48.1927",
            "6. volume": "152699091",
            "7. dividend amount": "0.0000"
        },
        "2020-07-31": {
            "1. open": "48.4100",
            "2. high": "53.5100",
            "3. low": "47.0200",
            "4. close": "48.8800",
            "5. adjusted close": "45.0758",
            "6. volume": "266501626",
            "7. dividend amount": "0.3500"
        },
        "2020-06-30": {
            "1. open": "44.5200",
            "2. high": "51.8500",
            "3. low": "43.9500",
            "4. close": "48.3000",
            "5. adjusted close": "44.2247",
            "6. volume": "296556852",
            "7. dividend amount": "0.0000"
        },
        "2020-05-29": {
            "1. open": "38.3500",
            "2. high": "47.3200",
            "3. low": "35.5300",
            "4. close": "44.2000",
            "5. adjusted close": "40.4707",
            "6. volume": "252483991",
            "7. dividend amount": "0.0000"
        },
        "2020-04-30": {
            "1. open": "31.6800",
            "2. high": "41.8500",
            "3. low": "31.1600",
            "4. close": "39.4300",
            "5. adjusted close": "36.1031",
            "6. volume": "346304903",
            "7. dividend amount": "0.3500"
        },
        "2020-03-31": {
            "1. open": "45.1100",
            "2. high": "46.9200",
            "3. low": "27.2000",
            "4. close": "34.0000",
            "5. adjusted close": "30.8664",
            "6. volume": "581088494",
            "7. dividend amount": "0.0000"
        },
        "2020-02-28": {
            "1. open": "52.6400",
            "2. high": "56.6600",
            "3. low": "43.6900",
            "4. close": "45.0300",
            "5. adjusted close": "40.8799",
            "6. volume": "311521112",
            "7. dividend amount": "0.0000"
        },
        "2020-01-31": {
            "1. open": "51.2000",
            "2. high": "57.5700",
            "3. low": "50.4600",
            "4. close": "52.2600",
            "5. adjusted close": "47.4435",
            "6. volume": "226779644",
            "7. dividend amount": "0.3500"
        },
        "2019-12-31": {
            "1. open": "49.5800",
            "2. high": "51.4400",
            "3. low": "47.4400",
            "4. close": "51.1200",
            "5. adjusted close": "46.1087",
            "6. volume": "176089830",
            "7. dividend amount": "0.0000"
        },
        "2019-11-29": {
            "1. open": "46.5200",
            "2. high": "49.9800",
            "3. low": "46.4600",
            "4. close": "49.4800",
            "5. adjusted close": "44.6295",
            "6. volume": "171937706",
            "7. dividend amount": "0.0000"
        },
        "2019-10-31": {
            "1. open": "42.5100",
            "2. high": "47.1600",
            "3. low": "39.3000",
            "4. close": "46.0500",
            "5. adjusted close": "41.5357",
            "6. volume": "233693434",
            "7. dividend amount": "0.3500"
        },
        "2019-09-30": {
            "1. open": "41.0400",
            "2. high": "45.4500",
            "3. low": "40.3500",
            "4. close": "42.6700",
            "5. adjusted close": "38.1981",
            "6. volume": "187799993",
            "7. dividend amount": "0.0000"
        },
        "2019-08-30": {
            "1. open": "44.4200",
            "2. high": "44.7400",
            "3. low": "38.7600",
            "4. close": "41.4900",
            "5. adjusted close": "37.1417",
            "6. volume": "248017113",
            "7. dividend amount": "0.0000"
        },
        "2019-07-31": {
            "1. open": "44.5900",
            "2. high": "45.7700",
            "3. low": "43.0200",
            "4. close": "44.5600",
            "5. adjusted close": "39.8900",
            "6. volume": "182752201",
            "7. dividend amount": "0.3500"
        },
        "2019-06-28": {
            "1. open": "40.7100",
            "2. high": "44.5700",
            "3. low": "40.4300",
            "4. close": "43.8100",
            "5. adjusted close": "38.9137",
            "6. volume": "185026027",
            "7. dividend amount": "0.0000"
        },
        "2019-05-31": {
            "1. open": "48.2000",
            "2. high": "48.6200",
            "3. low": "40.6000",
            "4. close": "40.6900",
            "5. adjusted close": "36.1424",
            "6. volume": "210435080",
            "7. dividend amount": "0.0000"
        },
        "2019-04-30": {
            "1. open": "42.7800",
            "2. high": "48.6700",
            "3. low": "42.7500",
            "4. close": "48.2500",
            "5. adjusted close": "42.8575",
            "6. volume": "242780022",
            "7. dividend amount": "0.3000"
        },
        "2019-03-29": {
            "1. open": "42.3500",
            "2. high": "44.8900",
            "3. low": "40.4000",
            "4. close": "42.2000",
            "5. adjusted close": "37.2530",
            "6. volume": "250727867",
            "7. dividend amount": "0.0000"
        },
        "2019-02-28": {
            "1. open": "42.3000",
            "2. high": "42.8600",
            "3. low": "40.1200",
            "4. close": "41.9800",
            "5. adjusted close": "37.0588",
            "6. volume": "210779050",
            "7. dividend amount": "0.0000"
        },
        "2019-01-31": {
            "1. open": "39.0200",
            "2. high": "45.1100",
            "3. low": "38.7600",
            "4. close": "42.3000",
            "5. adjusted close": "37.3413",
            "6. volume": "314951529",
            "7. dividend amount": "0.3000"
        },
        "2018-12-31": {
            "1. open": "45.0700",
            "2. high": "46.1400",
            "3. low": "36.7400",
            "4. close": "39.6500",
            "5. adjusted close": "34.7583",
            "6. volume": "307652171",
            "7. dividend amount": "0.0000"
        },
        "2018-11-30": {
            "1. open": "45.8200",
            "2. high": "46.9500",
            "3. low": "42.5400",
            "4. close": "44.3900",
            "5. adjusted close": "38.9135",
            "6. volume": "223856242",
            "7. dividend amount": "0.0000"
        },
        "2018-10-31": {
            "1. open": "46.9200",
            "2. high": "47.9300",
            "3. low": "42.8800",
            "4. close": "45.6600",
            "5. adjusted close": "40.0268",
            "6. volume": "313773851",
            "7. dividend amount": "0.3000"
        },
        "2018-09-28": {
            "1. open": "48.8600",
            "2. high": "50.3700",
            "3. low": "46.4000",
            "4. close": "46.5700",
            "5. adjusted close": "40.5511",
            "6. volume": "172175759",
            "7. dividend amount": "0.0000"
        },
        "2018-08-31": {
            "1. open": "50.9400",
            "2. high": "51.1800",
            "3. low": "47.0200",
            "4. close": "48.8300",
            "5. adjusted close": "42.5190",
            "6. volume": "188264616",
            "7. dividend amount": "0.0000"
        },
        "2018-07-31": {
            "1. open": "46.9600",
            "2. high": "51.5300",
            "3. low": "46.2800",
            "4. close": "50.5600",
            "5. adjusted close": "44.0255",
            "6. volume": "187438410",
            "7. dividend amount": "0.3000"
        },
        "2018-06-29": {
            "1. open": "50.9300",
            "2. high": "52.7200",
            "3. low": "47.1100",
            "4. close": "47.4000",
            "5. adjusted close": "41.0320",
            "6. volume": "213615075",
            "7. dividend amount": "0.0000"
        },
        "2018-05-31": {
            "1. open": "51.3900",
            "2. high": "55.6400",
            "3. low": "49.5100",
            "4. close": "50.1400",
            "5. adjusted close": "43.4039",
            "6. volume": "196362844",
            "7. dividend amount": "0.0000"
        },
        "2018-04-30": {
            "1. open": "53.8300",
            "2. high": "55.3900",
            "3. low": "51.5800",
            "4. close": "51.6200",
            "5. adjusted close": "44.6851",
            "6. volume": "223003739",
            "7. dividend amount": "0.2500"
        },
        "2018-03-29": {
            "1. open": "55.8900",
            "2. high": "59.3800",
            "3. low": "51.9700",
            "4. close": "53.9600",
            "5. adjusted close": "46.4866",
            "6. volume": "202147475",
            "7. dividend amount": "0.0000"
        },
        "2018-02-28": {
            "1. open": "56.5000",
            "2. high": "57.8200",
            "3. low": "50.0200",
            "4. close": "56.0200",
            "5. adjusted close": "48.2613",
            "6. volume": "192873258",
            "7. dividend amount": "0.0000"
        },
        "2018-01-31": {
            "1. open": "52.7600",
            "2. high": "58.0500",
            "3. low": "51.9200",
            "4. close": "56.5500",
            "5. adjusted close": "48.7179",
            "6. volume": "195348647",
            "7. dividend amount": "0.2500"
        },
        "2017-12-29": {
            "1. open": "51.8800",
            "2. high": "54.2500",
            "3. low": "50.7200",
            "4. close": "52.4700",
            "5. adjusted close": "45.0042",
            "6. volume": "150458472",
            "7. dividend amount": "0.0000"
        },
        "2017-11-30": {
            "1. open": "50.2200",
            "2. high": "52.5800",
            "3. low": "47.4200",
            "4. close": "51.6100",
            "5. adjusted close": "44.2666",
            "6. volume": "141004100",
            "7. dividend amount": "0.0000"
        },
        "2017-10-31": {
            "1. open": "48.1100",
            "2. high": "51.5200",
            "3. low": "47.7000",
            "4. close": "50.0000",
            "5. adjusted close": "42.8856",
            "6. volume": "176731891",
            "7. dividend amount": "0.2500"
        },
        "2017-09-29": {
            "1. open": "45.5900",
            "2. high": "48.4900",
            "3. low": "43.8400",
            "4. close": "48.1700",
            "5. adjusted close": "41.1123",
            "6. volume": "155501483",
            "7. dividend amount": "0.0000"
        },
        "2017-08-31": {
            "1. open": "47.2500",
            "2. high": "48.8983",
            "3. low": "44.3421",
            "4. close": "45.5000",
            "5. adjusted close": "38.8335",
            "6. volume": "174434927",
            "7. dividend amount": "0.0000"
        },
        "2017-07-31": {
            "1. open": "45.0000",
            "2. high": "48.0400",
            "3. low": "44.3200",
            "4. close": "46.9000",
            "5. adjusted close": "40.0284",
            "6. volume": "174885171",
            "7. dividend amount": "0.2500"
        },
        "2017-06-30": {
            "1. open": "41.9800",
            "2. high": "45.9800",
            "3. low": "41.7500",
            "4. close": "44.5600",
            "5. adjusted close": "37.8304",
            "6. volume": "210222790",
            "7. dividend amount": "0.0000"
        },
        "2017-05-31": {
            "1. open": "43.7600",
            "2. high": "44.0600",
            "3. low": "40.4300",
            "4. close": "41.7400",
            "5. adjusted close": "35.4363",
            "6. volume": "185847182",
            "7. dividend amount": "0.0000"
        },
        "2017-04-28": {
            "1. open": "42.8100",
            "2. high": "44.8600",
            "3. low": "40.5000",
            "4. close": "43.3700",
            "5. adjusted close": "36.8201",
            "6. volume": "220855647",
            "7. dividend amount": "0.2000"
        },
        "2017-03-31": {
            "1. open": "46.9500",
            "2. high": "47.3300",
            "3. low": "40.0600",
            "4. close": "42.8400",
            "5. adjusted close": "36.2039",
            "6. volume": "277879586",
            "7. dividend amount": "0.0000"
        },
        "2017-02-28": {
            "1. open": "43.3000",
            "2. high": "46.8200",
            "3. low": "41.8300",
            "4. close": "45.6700",
            "5. adjusted close": "38.5955",
            "6. volume": "209218544",
            "7. dividend amount": "0.0000"
        },
        "2017-01-31": {
            "1. open": "43.0900",
            "2. high": "44.6000",
            "3. low": "41.7700",
            "4. close": "42.4900",
            "5. adjusted close": "35.9081",
            "6. volume": "223847617",
            "7. dividend amount": "0.2000"
        },
        "2016-12-30": {
            "1. open": "41.7600",
            "2. high": "44.0400",
            "3. low": "41.1400",
            "4. close": "42.2500",
            "5. adjusted close": "35.5424",
            "6. volume": "239331697",
            "7. dividend amount": "0.0000"
        },
        "2016-11-30": {
            "1. open": "33.6800",
            "2. high": "41.6400",
            "3. low": "32.5600",
            "4. close": "41.3600",
            "5. adjusted close": "34.7937",
            "6. volume": "303742149",
            "7. dividend amount": "0.0000"
        },
        "2016-10-31": {
            "1. open": "32.0200",
            "2. high": "34.0300",
            "3. low": "30.9600",
            "4. close": "33.5700",
            "5. adjusted close": "28.2405",
            "6. volume": "225582587",
            "7. dividend amount": "0.2000"
        },
        "2016-09-30": {
            "1. open": "32.1400",
            "2. high": "32.4400",
            "3. low": "30.6200",
            "4. close": "32.0600",
            "5. adjusted close": "26.8116",
            "6. volume": "243215895",
            "7. dividend amount": "0.0000"
        },
        "2016-08-31": {
            "1. open": "28.8400",
            "2. high": "32.3100",
            "3. low": "27.7900",
            "4. close": "32.0600",
            "5. adjusted close": "26.8116",
            "6. volume": "258706669",
            "7. dividend amount": "0.0000"
        },
        "2016-07-29": {
            "1. open": "25.7700",
            "2. high": "29.3700",
            "3. low": "24.5700",
            "4. close": "28.7300",
            "5. adjusted close": "24.0268",
            "6. volume": "298000862",
            "7. dividend amount": "0.2000"
        },
        "2016-06-30": {
            "1. open": "27.1100",
            "2. high": "27.5700",
            "3. low": "23.1100",
            "4. close": "25.9800",
            "5. adjusted close": "21.5782",
            "6. volume": "359945802",
            "7. dividend amount": "0.0000"
        },
        "2016-05-31": {
            "1. open": "27.1000",
            "2. high": "28.2900",
            "3. low": "25.8500",
            "4. close": "27.3700",
            "5. adjusted close": "22.7327",
            "6. volume": "271739587",
            "7. dividend amount": "0.0000"
        },
        "2016-04-29": {
            "1. open": "24.8900",
            "2. high": "27.8800",
            "3. low": "23.5100",
            "4. close": "27.0600",
            "5. adjusted close": "22.4753",
            "6. volume": "338448199",
            "7. dividend amount": "0.1500"
        },
        "2016-03-31": {
            "1. open": "25.0900",
            "2. high": "26.6100",
            "3. low": "24.1200",
            "4. close": "25.0100",
            "5. adjusted close": "20.6600",
            "6. volume": "354416847",
            "7. dividend amount": "0.0000"
        },
        "2016-02-29": {
            "1. open": "25.7800",
            "2. high": "25.9300",
            "3. low": "21.1550",
            "4. close": "24.7000",
            "5. adjusted close": "20.4039",
            "6. volume": "379260666",
            "7. dividend amount": "0.0000"
        },
        "2016-01-29": {
            "1. open": "30.7000",
            "2. high": "31.7000",
            "3. low": "24.6700",
            "4. close": "25.8800",
            "5. adjusted close": "21.3787",
            "6. volume": "377959241",
            "7. dividend amount": "0.1500"
        },
        "2015-12-31": {
            "1. open": "34.6000",
            "2. high": "35.5800",
            "3. low": "31.1900",
            "4. close": "31.8100",
            "5. adjusted close": "26.1228",
            "6. volume": "251478136",
            "7. dividend amount": "0.0000"
        },
        "2015-11-30": {
            "1. open": "33.1000",
            "2. high": "35.7400",
            "3. low": "33.0200",
            "4. close": "34.3000",
            "5. adjusted close": "28.1677",
            "6. volume": "199501474",
            "7. dividend amount": "0.0000"
        },
        "2015-10-30": {
            "1. open": "31.4200",
            "2. high": "34.0800",
            "3. low": "30.1500",
            "4. close": "32.9700",
            "5. adjusted close": "27.0755",
            "6. volume": "334487614",
            "7. dividend amount": "0.1500"
        },
        "2015-09-30": {
            "1. open": "33.4000",
            "2. high": "35.0500",
            "3. low": "30.4700",
            "4. close": "31.5000",
            "5. adjusted close": "25.7527",
            "6. volume": "263296468",
            "7. dividend amount": "0.0000"
        },
        "2015-08-31": {
            "1. open": "38.9600",
            "2. high": "39.3500",
            "3. low": "30.4000",
            "4. close": "34.4500",
            "5. adjusted close": "28.1645",
            "6. volume": "261203276",
            "7. dividend amount": "0.0000"
        },
        "2015-07-31": {
            "1. open": "39.4600",
            "2. high": "41.0400",
            "3. low": "37.6500",
            "4. close": "38.8400",
            "5. adjusted close": "31.7535",
            "6. volume": "199018532",
            "7. dividend amount": "0.1500"
        },
        "2015-06-30": {
            "1. open": "38.4200",
            "2. high": "40.2600",
            "3. low": "38.1600",
            "4. close": "38.7900",
            "5. adjusted close": "31.5921",
            "6. volume": "166465405",
            "7. dividend amount": "0.0000"
        },
        "2015-05-29": {
            "1. open": "37.5000",
            "2. high": "38.8500",
            "3. low": "36.7600",
            "4. close": "38.2000",
            "5. adjusted close": "31.1115",
            "6. volume": "166220989",
            "7. dividend amount": "0.0000"
        },
        "2015-04-30": {
            "1. open": "35.7200",
            "2. high": "37.7000",
            "3. low": "35.3600",
            "4. close": "37.3100",
            "5. adjusted close": "30.3867",
            "6. volume": "192051874",
            "7. dividend amount": "0.1500"
        },
        "2015-03-31": {
            "1. open": "35.6400",
            "2. high": "37.2198",
            "3. low": "34.7750",
            "4. close": "35.6900",
            "5. adjusted close": "28.9501",
            "6. volume": "223705240",
            "7. dividend amount": "0.0000"
        },
        "2015-02-27": {
            "1. open": "33.9600",
            "2. high": "37.2000",
            "3. low": "33.7200",
            "4. close": "35.7900",
            "5. adjusted close": "29.0312",
            "6. volume": "183364105",
            "7. dividend amount": "0.0000"
        },
        "2015-01-30": {
            "1. open": "39.0500",
            "2. high": "39.1500",
            "3. low": "33.7300",
            "4. close": "33.8100",
            "5. adjusted close": "27.4251",
            "6. volume": "265941208",
            "7. dividend amount": "0.1000"
        },
        "2014-12-31": {
            "1. open": "35.0200",
            "2. high": "39.1900",
            "3. low": "34.5600",
            "4. close": "38.8000",
            "5. adjusted close": "31.3798",
            "6. volume": "201393117",
            "7. dividend amount": "0.0000"
        },
        "2014-11-28": {
            "1. open": "35.0500",
            "2. high": "36.1300",
            "3. low": "34.4300",
            "4. close": "35.1800",
            "5. adjusted close": "28.4521",
            "6. volume": "140824685",
            "7. dividend amount": "0.0000"
        },
        "2014-10-31": {
            "1. open": "34.3700",
            "2. high": "35.4000",
            "3. low": "31.3500",
            "4. close": "34.9500",
            "5. adjusted close": "28.2661",
            "6. volume": "267759468",
            "7. dividend amount": "0.1000"
        },
        "2014-09-30": {
            "1. open": "34.4200",
            "2. high": "36.4400",
            "3. low": "33.8200",
            "4. close": "34.5700",
            "5. adjusted close": "27.8777",
            "6. volume": "217966780",
            "7. dividend amount": "0.0000"
        },
        "2014-08-29": {
            "1. open": "32.1800",
            "2. high": "34.5700",
            "3. low": "31.1224",
            "4. close": "34.3100",
            "5. adjusted close": "27.6680",
            "6. volume": "147985300",
            "7. dividend amount": "0.0000"
        },
        "2014-07-31": {
            "1. open": "32.4100",
            "2. high": "33.6000",
            "3. low": "31.2000",
            "4. close": "32.3400",
            "5. adjusted close": "26.0794",
            "6. volume": "176508596",
            "7. dividend amount": "0.1000"
        },
        "2014-06-30": {
            "1. open": "30.8600",
            "2. high": "32.8200",
            "3. low": "30.4001",
            "4. close": "32.3300",
            "5. adjusted close": "25.9917",
            "6. volume": "184224800",
            "7. dividend amount": "0.0000"
        },
        "2014-05-30": {
            "1. open": "30.9100",
            "2. high": "31.4400",
            "3. low": "29.0200",
            "4. close": "30.8600",
            "5. adjusted close": "24.8099",
            "6. volume": "222266200",
            "7. dividend amount": "0.0000"
        },
        "2014-04-30": {
            "1. open": "31.3700",
            "2. high": "31.5900",
            "3. low": "28.3100",
            "4. close": "30.9300",
            "5. adjusted close": "24.8662",
            "6. volume": "279056100",
            "7. dividend amount": "0.1000"
        },
        "2014-03-31": {
            "1. open": "30.2400",
            "2. high": "33.2500",
            "3. low": "29.9300",
            "4. close": "31.1700",
            "5. adjusted close": "24.9759",
            "6. volume": "257790800",
            "7. dividend amount": "0.0000"
        },
        "2014-02-28": {
            "1. open": "29.5100",
            "2. high": "30.9400",
            "3. low": "28.7800",
            "4. close": "30.8000",
            "5. adjusted close": "24.6794",
            "6. volume": "258909600",
            "7. dividend amount": "0.0000"
        },
        "2014-01-31": {
            "1. open": "31.3300",
            "2. high": "33.5200",
            "3. low": "29.2800",
            "4. close": "29.5100",
            "5. adjusted close": "23.6458",
            "6. volume": "304437100",
            "7. dividend amount": "0.0500"
        },
        "2013-12-31": {
            "1. open": "31.5200",
            "2. high": "31.8500",
            "3. low": "30.0400",
            "4. close": "31.3600",
            "5. adjusted close": "25.0862",
            "6. volume": "219393800",
            "7. dividend amount": "0.0000"
        },
        "2013-11-29": {
            "1. open": "28.8900",
            "2. high": "31.8000",
            "3. low": "28.6900",
            "4. close": "31.3000",
            "5. adjusted close": "25.0382",
            "6. volume": "223654500",
            "7. dividend amount": "0.0000"
        },
        "2013-10-31": {
            "1. open": "26.9500",
            "2. high": "29.9700",
            "3. low": "26.4200",
            "4. close": "28.7300",
            "5. adjusted close": "22.9824",
            "6. volume": "290013033",
            "7. dividend amount": "0.0500"
        },
        "2013-09-30": {
            "1. open": "26.2200",
            "2. high": "29.4950",
            "3. low": "25.9500",
            "4. close": "26.9500",
            "5. adjusted close": "21.5218",
            "6. volume": "288068100",
            "7. dividend amount": "0.0000"
        },
        "2013-08-30": {
            "1. open": "27.5700",
            "2. high": "28.0200",
            "3. low": "25.2500",
            "4. close": "25.7600",
            "5. adjusted close": "20.5715",
            "6. volume": "225055100",
            "7. dividend amount": "0.0000"
        },
        "2013-07-31": {
            "1. open": "24.6400",
            "2. high": "27.9800",
            "3. low": "23.8300",
            "4. close": "27.2100",
            "5. adjusted close": "21.7295",
            "6. volume": "365586700",
            "7. dividend amount": "0.0500"
        },
        "2013-06-28": {
            "1. open": "26.0600",
            "2. high": "27.1700",
            "3. low": "23.9148",
            "4. close": "24.4300",
            "5. adjusted close": "19.4737",
            "6. volume": "436196100",
            "7. dividend amount": "0.0000"
        },
        "2013-05-31": {
            "1. open": "22.1100",
            "2. high": "26.4177",
            "3. low": "21.5400",
            "4. close": "25.9000",
            "5. adjusted close": "20.6455",
            "6. volume": "366420400",
            "7. dividend amount": "0.0000"
        },
        "2013-04-30": {
            "1. open": "21.9900",
            "2. high": "22.6300",
            "3. low": "20.1600",
            "4. close": "22.1500",
            "5. adjusted close": "17.6563",
            "6. volume": "469632500",
            "7. dividend amount": "0.0500"
        },
        "2013-03-28": {
            "1. open": "22.3900",
            "2. high": "23.6600",
            "3. low": "21.7800",
            "4. close": "21.9800",
            "5. adjusted close": "17.4799",
            "6. volume": "374171500",
            "7. dividend amount": "0.0000"
        },
        "2013-02-28": {
            "1. open": "23.0400",
            "2. high": "24.4700",
            "3. low": "21.7800",
            "4. close": "22.5500",
            "5. adjusted close": "17.9332",
            "6. volume": "378248600",
            "7. dividend amount": "0.0500"
        },
        "2013-01-31": {
            "1. open": "20.1601",
            "2. high": "23.0300",
            "3. low": "19.3200",
            "4. close": "22.8500",
            "5. adjusted close": "18.1333",
            "6. volume": "553471400",
            "7. dividend amount": "0.0000"
        },
        "2012-12-31": {
            "1. open": "17.0100",
            "2. high": "19.4500",
            "3. low": "16.3500",
            "4. close": "19.1200",
            "5. adjusted close": "15.1732",
            "6. volume": "345139100",
            "7. dividend amount": "0.0000"
        },
        "2012-11-30": {
            "1. open": "17.4100",
            "2. high": "18.2400",
            "3. low": "15.9500",
            "4. close": "16.8700",
            "5. adjusted close": "13.3877",
            "6. volume": "383097100",
            "7. dividend amount": "0.0000"
        },
        "2012-10-31": {
            "1. open": "16.9400",
            "2. high": "18.5700",
            "3. low": "16.7300",
            "4. close": "17.3800",
            "5. adjusted close": "13.7924",
            "6. volume": "441619400",
            "7. dividend amount": "0.0000"
        },
        "2012-09-28": {
            "1. open": "15.2900",
            "2. high": "18.5000",
            "3. low": "15.1300",
            "4. close": "16.7400",
            "5. adjusted close": "13.2845",
            "6. volume": "510560900",
            "7. dividend amount": "0.0000"
        },
        "2012-08-31": {
            "1. open": "13.7300",
            "2. high": "15.3400",
            "3. low": "12.9800",
            "4. close": "15.0000",
            "5. adjusted close": "11.9037",
            "6. volume": "388590100",
            "7. dividend amount": "0.0000"
        },
        "2012-07-31": {
            "1. open": "14.6100",
            "2. high": "15.2100",
            "3. low": "12.2900",
            "4. close": "13.6600",
            "5. adjusted close": "10.8403",
            "6. volume": "515490500",
            "7. dividend amount": "0.0500"
        },
        "2012-06-29": {
            "1. open": "12.9700",
            "2. high": "14.6100",
            "3. low": "12.2600",
            "4. close": "14.5900",
            "5. adjusted close": "11.5356",
            "6. volume": "602625100",
            "7. dividend amount": "0.0000"
        },
        "2012-05-31": {
            "1. open": "17.2300",
            "2. high": "17.6800",
            "3. low": "12.8100",
            "4. close": "13.3600",
            "5. adjusted close": "10.5631",
            "6. volume": "699975400",
            "7. dividend amount": "0.0000"
        },
        "2012-04-30": {
            "1. open": "19.6400",
            "2. high": "20.0500",
            "3. low": "16.6300",
            "4. close": "17.2800",
            "5. adjusted close": "13.6624",
            "6. volume": "531176000",
            "7. dividend amount": "0.0500"
        },
        "2012-03-30": {
            "1. open": "18.7400",
            "2. high": "21.1900",
            "3. low": "17.2400",
            "4. close": "19.6400",
            "5. adjusted close": "15.4833",
            "6. volume": "602498500",
            "7. dividend amount": "0.0000"
        },
        "2012-02-29": {
            "1. open": "19.1900",
            "2. high": "20.7000",
            "3. low": "18.2000",
            "4. close": "18.5400",
            "5. adjusted close": "14.6161",
            "6. volume": "474076600",
            "7. dividend amount": "0.0000"
        },
        "2012-01-31": {
            "1. open": "15.7600",
            "2. high": "18.8800",
            "3. low": "15.4300",
            "4. close": "18.6500",
            "5. adjusted close": "14.7029",
            "6. volume": "518774900",
            "7. dividend amount": "0.0500"
        },
        "2011-12-30": {
            "1. open": "14.5600",
            "2. high": "17.5000",
            "3. low": "14.0300",
            "4. close": "15.1300",
            "5. adjusted close": "11.8958",
            "6. volume": "646755700",
            "7. dividend amount": "0.0000"
        },
        "2011-11-30": {
            "1. open": "16.1400",
            "2. high": "17.7500",
            "3. low": "12.8600",
            "4. close": "14.7900",
            "5. adjusted close": "11.6285",
            "6. volume": "709168300",
            "7. dividend amount": "0.0000"
        },
        "2011-10-31": {
            "1. open": "13.5400",
            "2. high": "19.6682",
            "3. low": "11.5800",
            "4. close": "17.6400",
            "5. adjusted close": "13.8693",
            "6. volume": "890744800",
            "7. dividend amount": "0.0500"
        },
        "2011-09-30": {
            "1. open": "17.5000",
            "2. high": "17.5500",
            "3. low": "12.4900",
            "4. close": "13.5100",
            "5. adjusted close": "10.5948",
            "6. volume": "620746500",
            "7. dividend amount": "0.0000"
        },
        "2011-08-31": {
            "1. open": "22.7500",
            "2. high": "22.8600",
            "3. low": "15.2100",
            "4. close": "17.5000",
            "5. adjusted close": "13.7238",
            "6. volume": "706456800",
            "7. dividend amount": "0.0000"
        },
        "2011-07-29": {
            "1. open": "23.0800",
            "2. high": "24.4600",
            "3. low": "20.1800",
            "4. close": "22.2500",
            "5. adjusted close": "17.4489",
            "6. volume": "434624700",
            "7. dividend amount": "0.0500"
        },
        "2011-06-30": {
            "1. open": "24.0200",
            "2. high": "24.0500",
            "3. low": "21.7600",
            "4. close": "23.0100",
            "5. adjusted close": "18.0049",
            "6. volume": "374008300",
            "7. dividend amount": "0.0000"
        },
        "2011-05-31": {
            "1. open": "26.2800",
            "2. high": "26.4900",
            "3. low": "23.3300",
            "4. close": "24.1600",
            "5. adjusted close": "18.9048",
            "6. volume": "248611200",
            "7. dividend amount": "0.0000"
        },
        "2011-04-29": {
            "1. open": "27.4000",
            "2. high": "28.2400",
            "3. low": "25.3200",
            "4. close": "26.1500",
            "5. adjusted close": "20.4619",
            "6. volume": "250474600",
            "7. dividend amount": "0.0500"
        },
        "2011-03-31": {
            "1. open": "29.6900",
            "2. high": "29.7800",
            "3. low": "26.7000",
            "4. close": "27.3200",
            "5. adjusted close": "21.3356",
            "6. volume": "247822779",
            "7. dividend amount": "0.0000"
        },
        "2011-02-28": {
            "1. open": "29.5400",
            "2. high": "31.0400",
            "3. low": "28.8650",
            "4. close": "29.6800",
            "5. adjusted close": "23.1787",
            "6. volume": "205727800",
            "7. dividend amount": "0.0000"
        },
        "2011-01-31": {
            "1. open": "27.6300",
            "2. high": "30.2500",
            "3. low": "27.4800",
            "4. close": "29.4000",
            "5. adjusted close": "22.9600",
            "6. volume": "345080600",
            "7. dividend amount": "0.0500"
        },
        "2010-12-31": {
            "1. open": "24.8200",
            "2. high": "27.7700",
            "3. low": "24.7300",
            "4. close": "27.2100",
            "5. adjusted close": "21.2142",
            "6. volume": "248603200",
            "7. dividend amount": "0.0000"
        },
        "2010-11-30": {
            "1. open": "24.9500",
            "2. high": "27.3600",
            "3. low": "24.3700",
            "4. close": "24.4600",
            "5. adjusted close": "19.0701",
            "6. volume": "321001100",
            "7. dividend amount": "0.0000"
        },
        "2010-10-29": {
            "1. open": "24.9300",
            "2. high": "26.2300",
            "3. low": "23.9500",
            "4. close": "24.8700",
            "5. adjusted close": "19.3898",
            "6. volume": "338001300",
            "7. dividend amount": "0.0500"
        },
        "2010-09-30": {
            "1. open": "25.0500",
            "2. high": "27.8000",
            "3. low": "24.1800",
            "4. close": "24.6800",
            "5. adjusted close": "19.2023",
            "6. volume": "298774100",
            "7. dividend amount": "0.0000"
        },
        "2010-08-31": {
            "1. open": "27.4300",
            "2. high": "28.0500",
            "3. low": "24.2400",
            "4. close": "24.6900",
            "5. adjusted close": "19.2101",
            "6. volume": "228157600",
            "7. dividend amount": "0.0000"
        },
        "2010-07-30": {
            "1. open": "23.2100",
            "2. high": "27.8900",
            "3. low": "22.4000",
            "4. close": "26.9900",
            "5. adjusted close": "20.9996",
            "6. volume": "357025800",
            "7. dividend amount": "0.0500"
        },
        "2010-06-30": {
            "1. open": "26.7900",
            "2. high": "27.3900",
            "3. low": "23.1400",
            "4. close": "23.2100",
            "5. adjusted close": "18.0252",
            "6. volume": "368470200",
            "7. dividend amount": "0.0000"
        },
        "2010-05-28": {
            "1. open": "30.2500",
            "2. high": "30.6000",
            "3. low": "24.7600",
            "4. close": "27.1100",
            "5. adjusted close": "21.0540",
            "6. volume": "480372700",
            "7. dividend amount": "0.0000"
        },
        "2010-04-30": {
            "1. open": "29.4600",
            "2. high": "32.2900",
            "3. low": "28.6700",
            "4. close": "30.2200",
            "5. adjusted close": "23.4693",
            "6. volume": "484398200",
            "7. dividend amount": "0.0500"
        },
        "2010-03-31": {
            "1. open": "28.3000",
            "2. high": "30.7900",
            "3. low": "28.1100",
            "4. close": "29.2900",
            "5. adjusted close": "22.7096",
            "6. volume": "387032700",
            "7. dividend amount": "0.0000"
        },
        "2010-02-26": {
            "1. open": "26.9500",
            "2. high": "28.4300",
            "3. low": "26.1500",
            "4. close": "28.1800",
            "5. adjusted close": "21.8490",
            "6. volume": "341901000",
            "7. dividend amount": "0.0000"
        },
        "2010-01-29": {
            "1. open": "30.7000",
            "2. high": "33.2700",
            "3. low": "26.6500",
            "4. close": "26.7800",
            "5. adjusted close": "20.7635",
            "6. volume": "455657800",
            "7. dividend amount": "0.0500"
        },
        "2009-12-31": {
            "1. open": "31.7700",
            "2. high": "31.9700",
            "3. low": "28.8100",
            "4. close": "29.6000",
            "5. adjusted close": "22.9090",
            "6. volume": "266866000",
            "7. dividend amount": "0.0000"
        },
        "2009-11-30": {
            "1. open": "32.1300",
            "2. high": "34.5500",
            "3. low": "29.9900",
            "4. close": "31.5800",
            "5. adjusted close": "24.4414",
            "6. volume": "277394600",
            "7. dividend amount": "0.0000"
        },
        "2009-10-30": {
            "1. open": "30.6700",
            "2. high": "35.7800",
            "3. low": "28.7500",
            "4. close": "32.1200",
            "5. adjusted close": "24.8593",
            "6. volume": "453506300",
            "7. dividend amount": "0.0500"
        },
        "2009-09-30": {
            "1. open": "28.8300",
            "2. high": "33.3299",
            "3. low": "27.0100",
            "4. close": "30.8800",
            "5. adjusted close": "23.8627",
            "6. volume": "457542200",
            "7. dividend amount": "0.0000"
        },
        "2009-08-31": {
            "1. open": "28.9300",
            "2. high": "32.0000",
            "3. low": "28.1000",
            "4. close": "28.9600",
            "5. adjusted close": "22.3790",
            "6. volume": "367115200",
            "7. dividend amount": "0.0000"
        },
        "2009-07-31": {
            "1. open": "28.5800",
            "2. high": "29.3300",
            "3. low": "24.8500",
            "4. close": "28.5000",
            "5. adjusted close": "22.0235",
            "6. volume": "520044000",
            "7. dividend amount": "0.0500"
        },
        "2009-06-30": {
            "1. open": "30.6700",
            "2. high": "31.9880",
            "3. low": "26.1300",
            "4. close": "28.5100",
            "5. adjusted close": "21.9908",
            "6. volume": "620787100",
            "7. dividend amount": "0.0000"
        },
        "2009-05-29": {
            "1. open": "23.7400",
            "2. high": "30.3500",
            "3. low": "23.6900",
            "4. close": "30.3200",
            "5. adjusted close": "23.3869",
            "6. volume": "821979100",
            "7. dividend amount": "0.0000"
        },
        "2009-04-30": {
            "1. open": "22.1900",
            "2. high": "27.3500",
            "3. low": "20.6900",
            "4. close": "23.6400",
            "5. adjusted close": "18.2344",
            "6. volume": "1048608400",
            "7. dividend amount": "0.0667"
        },
        "2009-03-31": {
            "1. open": "18.8600",
            "2. high": "27.2700",
            "3. low": "16.1200",
            "4. close": "22.7700",
            "5. adjusted close": "17.5079",
            "6. volume": "1269247700",
            "7. dividend amount": "0.0000"
        },
        "2009-02-27": {
            "1. open": "19.6000",
            "2. high": "24.4400",
            "3. low": "18.1100",
            "4. close": "19.5400",
            "5. adjusted close": "15.0244",
            "6. volume": "819625500",
            "7. dividend amount": "0.0000"
        },
        "2009-01-30": {
            "1. open": "16.0100",
            "2. high": "23.4200",
            "3. low": "13.1000",
            "4. close": "20.2300",
            "5. adjusted close": "15.5549",
            "6. volume": "749151800",
            "7. dividend amount": "0.2700"
        },
        "2008-12-31": {
            "1. open": "13.9300",
            "2. high": "17.9300",
            "3. low": "10.8500",
            "4. close": "16.0400",
            "5. adjusted close": "12.1901",
            "6. volume": "622291500",
            "7. dividend amount": "0.0000"
        },
        "2008-11-28": {
            "1. open": "17.8800",
            "2. high": "19.2600",
            "3. low": "8.8000",
            "4. close": "14.7500",
            "5. adjusted close": "11.2097",
            "6. volume": "714062900",
            "7. dividend amount": "0.0000"
        },
        "2008-10-31": {
            "1. open": "22.7200",
            "2. high": "26.7300",
            "3. low": "6.7100",
            "4. close": "17.4700",
            "5. adjusted close": "13.2769",
            "6. volume": "1596904700",
            "7. dividend amount": "0.2700"
        },
        "2008-09-30": {
            "1. open": "41.9600",
            "2. high": "44.5000",
            "3. low": "11.7000",
            "4. close": "23.0000",
            "5. adjusted close": "17.2231",
            "6. volume": "1353630300",
            "7. dividend amount": "0.0000"
        },
        "2008-08-29": {
            "1. open": "39.6700",
            "2. high": "46.5800",
            "3. low": "36.2000",
            "4. close": "40.8300",
            "5. adjusted close": "30.5747",
            "6. volume": "352754400",
            "7. dividend amount": "0.0000"
        },
        "2008-07-31": {
            "1. open": "35.4800",
            "2. high": "40.3500",
            "3. low": "29.6000",
            "4. close": "39.4800",
            "5. adjusted close": "29.5638",
            "6. volume": "538883900",
            "7. dividend amount": "0.2700"
        },
        "2008-06-30": {
            "1. open": "44.2000",
            "2. high": "44.8100",
            "3. low": "35.7200",
            "4. close": "36.0700",
            "5. adjusted close": "26.7974",
            "6. volume": "470457000",
            "7. dividend amount": "0.0000"
        },
        "2008-05-30": {
            "1. open": "48.8600",
            "2. high": "51.4200",
            "3. low": "41.1200",
            "4. close": "44.2300",
            "5. adjusted close": "32.8597",
            "6. volume": "238358800",
            "7. dividend amount": "0.0000"
        },
        "2008-04-30": {
            "1. open": "48.0300",
            "2. high": "51.5500",
            "3. low": "42.4900",
            "4. close": "48.6000",
            "5. adjusted close": "36.1063",
            "6. volume": "295489300",
            "7. dividend amount": "0.2700"
        },
        "2008-03-31": {
            "1. open": "42.1300",
            "2. high": "51.8000",
            "3. low": "33.5600",
            "4. close": "45.7000",
            "5. adjusted close": "33.7542",
            "6. volume": "489216800",
            "7. dividend amount": "0.0000"
        },
        "2008-02-29": {
            "1. open": "48.8600",
            "2. high": "49.4500",
            "3. low": "40.7600",
            "4. close": "42.1200",
            "5. adjusted close": "31.1100",
            "6. volume": "325832100",
            "7. dividend amount": "0.0000"
        },
        "2008-01-31": {
            "1. open": "52.9800",
            "2. high": "53.4000",
            "3. low": "42.5700",
            "4. close": "49.3400",
            "5. adjusted close": "36.4427",
            "6. volume": "382160500",
            "7. dividend amount": "0.2700"
        },
        "2007-12-31": {
            "1. open": "51.7900",
            "2. high": "55.3900",
            "3. low": "47.2500",
            "4. close": "53.1100",
            "5. adjusted close": "39.0066",
            "6. volume": "329729200",
            "7. dividend amount": "0.0000"
        },
        "2007-11-30": {
            "1. open": "65.0200",
            "2. high": "65.0200",
            "3. low": "47.5600",
            "4. close": "52.7200",
            "5. adjusted close": "38.7201",
            "6. volume": "392256700",
            "7. dividend amount": "0.0000"
        },
        "2007-10-31": {
            "1. open": "62.6000",
            "2. high": "69.2300",
            "3. low": "60.0000",
            "4. close": "67.2600",
            "5. adjusted close": "49.3990",
            "6. volume": "222344300",
            "7. dividend amount": "0.2700"
        },
        "2007-09-28": {
            "1. open": "62.5400",
            "2. high": "69.8700",
            "3. low": "60.5000",
            "4. close": "63.0000",
            "5. adjusted close": "46.0860",
            "6. volume": "207491400",
            "7. dividend amount": "0.0000"
        },
        "2007-08-31": {
            "1. open": "62.9400",
            "2. high": "66.8000",
            "3. low": "54.9000",
            "4. close": "62.3700",
            "5. adjusted close": "45.6251",
            "6. volume": "345192300",
            "7. dividend amount": "0.0000"
        },
        "2007-07-31": {
            "1. open": "70.9400",
            "2. high": "73.6400",
            "3. low": "61.5000",
            "4. close": "63.8700",
            "5. adjusted close": "46.7224",
            "6. volume": "240312700",
            "7. dividend amount": "14.5200"
        },
        "2007-06-29": {
            "1. open": "85.3000",
            "2. high": "90.9500",
            "3. low": "82.7300",
            "4. close": "83.8800",
            "5. adjusted close": "50.9484",
            "6. volume": "190019100",
            "7. dividend amount": "0.0000"
        },
        "2007-05-31": {
            "1. open": "84.5000",
            "2. high": "87.4400",
            "3. low": "82.5100",
            "4. close": "85.0400",
            "5. adjusted close": "51.6529",
            "6. volume": "89771900",
            "7. dividend amount": "0.0000"
        },
        "2007-04-30": {
            "1. open": "78.8400",
            "2. high": "85.1700",
            "3. low": "77.2600",
            "4. close": "84.0100",
            "5. adjusted close": "51.0273",
            "6. volume": "109550200",
            "7. dividend amount": "0.2700"
        },
        "2007-03-30": {
            "1. open": "72.6700",
            "2. high": "82.0000",
            "3. low": "70.3000",
            "4. close": "78.7600",
            "5. adjusted close": "47.6764",
            "6. volume": "190208500",
            "7. dividend amount": "0.0000"
        },
        "2007-02-28": {
            "1. open": "83.4600",
            "2. high": "84.3900",
            "3. low": "73.0400",
            "4. close": "74.9200",
            "5. adjusted close": "45.3519",
            "6. volume": "101179000",
            "7. dividend amount": "0.0000"
        },
        "2007-01-31": {
            "1. open": "81.9300",
            "2. high": "84.6600",
            "3. low": "79.6000",
            "4. close": "82.7900",
            "5. adjusted close": "50.1159",
            "6. volume": "91958100",
            "7. dividend amount": "0.2700"
        },
        "2006-12-29": {
            "1. open": "76.3000",
            "2. high": "83.4000",
            "3. low": "74.5100",
            "4. close": "81.4300",
            "5. adjusted close": "49.1300",
            "6. volume": "78998400",
            "7. dividend amount": "0.0000"
        },
        "2006-11-30": {
            "1. open": "76.6000",
            "2. high": "80.0000",
            "3. low": "73.3000",
            "4. close": "76.1600",
            "5. adjusted close": "45.9504",
            "6. volume": "83709800",
            "7. dividend amount": "0.0000"
        },
        "2006-10-31": {
            "1. open": "72.2500",
            "2. high": "78.2000",
            "3. low": "72.2500",
            "4. close": "76.4300",
            "5. adjusted close": "46.1133",
            "6. volume": "78895600",
            "7. dividend amount": "0.2700"
        },
        "2006-09-29": {
            "1. open": "66.1500",
            "2. high": "73.6500",
            "3. low": "65.2600",
            "4. close": "72.9100",
            "5. adjusted close": "43.8313",
            "6. volume": "95916500",
            "7. dividend amount": "0.0000"
        },
        "2006-08-31": {
            "1. open": "66.0000",
            "2. high": "69.5000",
            "3. low": "63.8000",
            "4. close": "65.7900",
            "5. adjusted close": "39.5509",
            "6. volume": "100760100",
            "7. dividend amount": "0.0000"
        },
        "2006-07-31": {
            "1. open": "63.3900",
            "2. high": "66.6600",
            "3. low": "60.1800",
            "4. close": "66.5000",
            "5. adjusted close": "39.9778",
            "6. volume": "85767400",
            "7. dividend amount": "0.2700"
        },
        "2006-06-30": {
            "1. open": "59.3500",
            "2. high": "63.4900",
            "3. low": "54.5200",
            "4. close": "63.2100",
            "5. adjusted close": "37.8368",
            "6. volume": "115983600",
            "7. dividend amount": "0.0000"
        },
        "2006-05-31": {
            "1. open": "64.6500",
            "2. high": "66.0000",
            "3. low": "57.5800",
            "4. close": "59.6200",
            "5. adjusted close": "35.6879",
            "6. volume": "84910800",
            "7. dividend amount": "0.0000"
        },
        "2006-04-28": {
            "1. open": "62.6200",
            "2. high": "65.7900",
            "3. low": "62.4500",
            "4. close": "64.3000",
            "5. adjusted close": "38.4893",
            "6. volume": "72187300",
            "7. dividend amount": "0.2700"
        },
        "2006-03-31": {
            "1. open": "59.7000",
            "2. high": "64.2300",
            "3. low": "58.4100",
            "4. close": "62.8200",
            "5. adjusted close": "37.4422",
            "6. volume": "103760100",
            "7. dividend amount": "0.0000"
        },
        "2006-02-28": {
            "1. open": "61.1000",
            "2. high": "62.1500",
            "3. low": "59.2100",
            "4. close": "59.6600",
            "5. adjusted close": "35.5588",
            "6. volume": "63383200",
            "7. dividend amount": "0.0000"
        },
        "2006-01-31": {
            "1. open": "57.1700",
            "2. high": "61.9100",
            "3. low": "56.7400",
            "4. close": "61.4500",
            "5. adjusted close": "36.6257",
            "6. volume": "93261600",
            "7. dividend amount": "0.2700"
        },
        "2005-12-30": {
            "1. open": "56.4000",
            "2. high": "58.6700",
            "3. low": "55.8900",
            "4. close": "56.7400",
            "5. adjusted close": "33.6658",
            "6. volume": "91064600",
            "7. dividend amount": "0.0000"
        },
        "2005-11-30": {
            "1. open": "54.1000",
            "2. high": "57.9800",
            "3. low": "51.9000",
            "4. close": "56.0300",
            "5. adjusted close": "33.2445",
            "6. volume": "112677500",
            "7. dividend amount": "0.0000"
        },
        "2005-10-31": {
            "1. open": "53.9300",
            "2. high": "55.0800",
            "3. low": "50.7300",
            "4. close": "54.4100",
            "5. adjusted close": "32.2833",
            "6. volume": "102029100",
            "7. dividend amount": "0.2700"
        },
        "2005-09-30": {
            "1. open": "50.8700",
            "2. high": "54.0100",
            "3. low": "50.6100",
            "4. close": "53.9400",
            "5. adjusted close": "31.8390",
            "6. volume": "103545900",
            "7. dividend amount": "0.0000"
        },
        "2005-08-31": {
            "1. open": "53.1600",
            "2. high": "54.5000",
            "3. low": "50.1800",
            "4. close": "50.8700",
            "5. adjusted close": "30.0269",
            "6. volume": "97778500",
            "7. dividend amount": "0.0000"
        },
        "2005-07-29": {
            "1. open": "52.7500",
            "2. high": "54.6100",
            "3. low": "52.4200",
            "4. close": "53.0500",
            "5. adjusted close": "31.3136",
            "6. volume": "93451800",
            "7. dividend amount": "0.2700"
        },
        "2005-06-30": {
            "1. open": "49.2000",
            "2. high": "53.7600",
            "3. low": "48.6100",
            "4. close": "52.4700",
            "5. adjusted close": "30.8157",
            "6. volume": "167708000",
            "7. dividend amount": "0.0000"
        },
        "2005-05-31": {
            "1. open": "50.3100",
            "2. high": "50.8600",
            "3. low": "47.6600",
            "4. close": "48.9600",
            "5. adjusted close": "28.7543",
            "6. volume": "158369500",
            "7. dividend amount": "0.0000"
        },
        "2005-04-29": {
            "1. open": "57.4800",
            "2. high": "60.1000",
            "3. low": "49.7700",
            "4. close": "52.6200",
            "5. adjusted close": "30.9038",
            "6. volume": "207843800",
            "7. dividend amount": "0.2700"
        },
        "2005-03-31": {
            "1. open": "56.4700",
            "2. high": "60.4000",
            "3. low": "53.5800",
            "4. close": "57.2500",
            "5. adjusted close": "33.4530",
            "6. volume": "154288400",
            "7. dividend amount": "0.0000"
        },
        "2005-02-28": {
            "1. open": "56.4500",
            "2. high": "60.5100",
            "3. low": "56.1500",
            "4. close": "56.4700",
            "5. adjusted close": "32.9972",
            "6. volume": "88314100",
            "7. dividend amount": "0.0000"
        },
        "2005-01-31": {
            "1. open": "55.9700",
            "2. high": "56.9000",
            "3. low": "53.5300",
            "4. close": "55.9600",
            "5. adjusted close": "32.6992",
            "6. volume": "93525600",
            "7. dividend amount": "0.2700"
        },
        "2004-12-31": {
            "1. open": "51.0000",
            "2. high": "55.9600",
            "3. low": "51.0000",
            "4. close": "55.5200",
            "5. adjusted close": "32.2844",
            "6. volume": "102079800",
            "7. dividend amount": "0.0000"
        },
        "2004-11-30": {
            "1. open": "51.3000",
            "2. high": "54.0000",
            "3. low": "50.4300",
            "4. close": "50.7500",
            "5. adjusted close": "29.5107",
            "6. volume": "90566200",
            "7. dividend amount": "0.0000"
        },
        "2004-10-29": {
            "1. open": "49.4500",
            "2. high": "52.3400",
            "3. low": "47.2700",
            "4. close": "51.0900",
            "5. adjusted close": "29.7084",
            "6. volume": "91058800",
            "7. dividend amount": "0.2500"
        },
        "2004-09-30": {
            "1. open": "50.7700",
            "2. high": "53.1900",
            "3. low": "48.0500",
            "4. close": "49.3000",
            "5. adjusted close": "28.5233",
            "6. volume": "100543100",
            "7. dividend amount": "0.0000"
        },
        "2004-08-31": {
            "1. open": "48.7000",
            "2. high": "52.1000",
            "3. low": "46.5400",
            "4. close": "50.7300",
            "5. adjusted close": "29.3507",
            "6. volume": "78685500",
            "7. dividend amount": "0.0000"
        },
        "2004-07-30": {
            "1. open": "52.6500",
            "2. high": "53.0800",
            "3. low": "46.9200",
            "4. close": "49.3300",
            "5. adjusted close": "28.5407",
            "6. volume": "107081200",
            "7. dividend amount": "0.2500"
        },
        "2004-06-30": {
            "1. open": "53.6700",
            "2. high": "54.7400",
            "3. low": "50.5200",
            "4. close": "52.7700",
            "5. adjusted close": "30.3787",
            "6. volume": "82495200",
            "7. dividend amount": "0.0000"
        },
        "2004-05-28": {
            "1. open": "51.5000",
            "2. high": "54.8000",
            "3. low": "50.2200",
            "4. close": "53.5100",
            "5. adjusted close": "30.8047",
            "6. volume": "102956100",
            "7. dividend amount": "0.0000"
        },
        "2004-04-30": {
            "1. open": "57.4800",
            "2. high": "58.5000",
            "3. low": "51.0700",
            "4. close": "51.3900",
            "5. adjusted close": "29.5842",
            "6. volume": "126777200",
            "7. dividend amount": "0.2500"
        },
        "2004-03-31": {
            "1. open": "60.7500",
            "2. high": "62.8300",
            "3. low": "55.6900",
            "4. close": "57.3000",
            "5. adjusted close": "32.8424",
            "6. volume": "113844200",
            "7. dividend amount": "0.0000"
        },
        "2004-02-27": {
            "1. open": "58.0700",
            "2. high": "62.1600",
            "3. low": "55.9200",
            "4. close": "59.7600",
            "5. adjusted close": "34.2523",
            "6. volume": "81538500",
            "7. dividend amount": "0.0000"
        },
        "2004-01-30": {
            "1. open": "57.8900",
            "2. high": "60.9000",
            "3. low": "56.7500",
            "4. close": "58.2100",
            "5. adjusted close": "33.3639",
            "6. volume": "83420400",
            "7. dividend amount": "0.2500"
        },
        "2003-12-31": {
            "1. open": "55.5300",
            "2. high": "58.7800",
            "3. low": "54.4000",
            "4. close": "57.8700",
            "5. adjusted close": "33.0262",
            "6. volume": "74578700",
            "7. dividend amount": "0.0000"
        },
        "2003-11-28": {
            "1. open": "55.1700",
            "2. high": "58.0700",
            "3. low": "52.5400",
            "4. close": "55.2800",
            "5. adjusted close": "31.5481",
            "6. volume": "85832500",
            "7. dividend amount": "0.0000"
        },
        "2003-10-31": {
            "1. open": "50.8000",
            "2. high": "55.2300",
            "3. low": "50.7200",
            "4. close": "54.8700",
            "5. adjusted close": "31.3141",
            "6. volume": "93330300",
            "7. dividend amount": "0.2300"
        },
        "2003-09-30": {
            "1. open": "48.7900",
            "2. high": "53.1000",
            "3. low": "47.8100",
            "4. close": "50.4600",
            "5. adjusted close": "28.6735",
            "6. volume": "120396800",
            "7. dividend amount": "0.0000"
        },
        "2003-08-29": {
            "1. open": "47.1900",
            "2. high": "49.9500",
            "3. low": "44.7800",
            "4. close": "48.7900",
            "5. adjusted close": "27.7245",
            "6. volume": "81762800",
            "7. dividend amount": "0.0000"
        },
        "2003-07-31": {
            "1. open": "42.6400",
            "2. high": "49.4000",
            "3. low": "42.4200",
            "4. close": "47.4400",
            "5. adjusted close": "26.9574",
            "6. volume": "118608200",
            "7. dividend amount": "0.2300"
        },
        "2003-06-30": {
            "1. open": "46.5500",
            "2. high": "50.4900",
            "3. low": "42.6800",
            "4. close": "42.7500",
            "5. adjusted close": "24.1749",
            "6. volume": "129789500",
            "7. dividend amount": "0.0000"
        },
        "2003-05-30": {
            "1. open": "44.7500",
            "2. high": "46.1000",
            "3. low": "41.7800",
            "4. close": "45.7500",
            "5. adjusted close": "25.8713",
            "6. volume": "105023000",
            "7. dividend amount": "0.0000"
        },
        "2003-04-30": {
            "1. open": "38.6800",
            "2. high": "48.0300",
            "3. low": "38.4000",
            "4. close": "44.7500",
            "5. adjusted close": "25.3058",
            "6. volume": "127882300",
            "7. dividend amount": "0.2300"
        },
        "2003-03-31": {
            "1. open": "37.2500",
            "2. high": "41.7300",
            "3. low": "32.4600",
            "4. close": "38.3500",
            "5. adjusted close": "21.5669",
            "6. volume": "133061100",
            "7. dividend amount": "0.0000"
        },
        "2003-02-28": {
            "1. open": "37.9100",
            "2. high": "38.8000",
            "3. low": "34.3200",
            "4. close": "36.8500",
            "5. adjusted close": "20.7234",
            "6. volume": "92408500",
            "7. dividend amount": "0.0000"
        },
        "2003-01-31": {
            "1. open": "40.1600",
            "2. high": "44.3900",
            "3. low": "36.7500",
            "4. close": "37.9000",
            "5. adjusted close": "21.3139",
            "6. volume": "101396500",
            "7. dividend amount": "0.2300"
        },
        "2002-12-31": {
            "1. open": "46.0000",
            "2. high": "46.7000",
            "3. low": "39.3900",
            "4. close": "39.9200",
            "5. adjusted close": "22.3274",
            "6. volume": "97055800",
            "7. dividend amount": "0.0000"
        },
        "2002-11-29": {
            "1. open": "38.6000",
            "2. high": "46.8300",
            "3. low": "37.9500",
            "4. close": "45.2400",
            "5. adjusted close": "25.3029",
            "6. volume": "108333100",
            "7. dividend amount": "0.0000"
        },
        "2002-10-31": {
            "1. open": "34.0200",
            "2. high": "39.4100",
            "3. low": "28.8000",
            "4. close": "38.9200",
            "5. adjusted close": "21.7681",
            "6. volume": "151581000",
            "7. dividend amount": "0.2300"
        },
        "2002-09-30": {
            "1. open": "41.6200",
            "2. high": "43.7100",
            "3. low": "32.7000",
            "4. close": "33.8800",
            "5. adjusted close": "18.8219",
            "6. volume": "112682700",
            "7. dividend amount": "0.0000"
        },
        "2002-08-30": {
            "1. open": "39.7700",
            "2. high": "46.5000",
            "3. low": "36.3100",
            "4. close": "42.7200",
            "5. adjusted close": "23.7329",
            "6. volume": "107538300",
            "7. dividend amount": "0.0000"
        },
        "2002-07-31": {
            "1. open": "43.5900",
            "2. high": "44.0900",
            "3. low": "33.5000",
            "4. close": "40.3500",
            "5. adjusted close": "22.4162",
            "6. volume": "146020400",
            "7. dividend amount": "0.2300"
        },
        "2002-06-28": {
            "1. open": "45.4000",
            "2. high": "45.9400",
            "3. low": "39.8000",
            "4. close": "43.0800",
            "5. adjusted close": "23.8007",
            "6. volume": "107100800",
            "7. dividend amount": "0.0000"
        },
        "2002-05-31": {
            "1. open": "47.5000",
            "2. high": "50.6800",
            "3. low": "43.9200",
            "4. close": "45.4600",
            "5. adjusted close": "25.1156",
            "6. volume": "115530600",
            "7. dividend amount": "0.0000"
        },
        "2002-04-30": {
            "1. open": "57.0600",
            "2. high": "57.2900",
            "3. low": "46.5500",
            "4. close": "47.7200",
            "5. adjusted close": "26.3642",
            "6. volume": "122271000",
            "7. dividend amount": "0.2300"
        },
        "2002-03-28": {
            "1. open": "49.2000",
            "2. high": "58.2700",
            "3. low": "48.5000",
            "4. close": "57.3100",
            "5. adjusted close": "31.5322",
            "6. volume": "98788800",
            "7. dividend amount": "0.0000"
        },
        "2002-02-28": {
            "1. open": "54.1200",
            "2. high": "54.2000",
            "3. low": "45.9000",
            "4. close": "49.1200",
            "5. adjusted close": "27.0260",
            "6. volume": "116867300",
            "7. dividend amount": "0.0000"
        },
        "2002-01-31": {
            "1. open": "55.9200",
            "2. high": "60.0200",
            "3. low": "50.2000",
            "4. close": "55.0000",
            "5. adjusted close": "30.2612",
            "6. volume": "106193700",
            "7. dividend amount": "0.2300"
        },
        "2001-12-31": {
            "1. open": "53.5500",
            "2. high": "57.6500",
            "3. low": "51.3500",
            "4. close": "55.9400",
            "5. adjusted close": "30.6576",
            "6. volume": "86601200",
            "7. dividend amount": "0.0000"
        },
        "2001-11-30": {
            "1. open": "48.9500",
            "2. high": "59.6000",
            "3. low": "48.0600",
            "4. close": "55.5000",
            "5. adjusted close": "30.4165",
            "6. volume": "90346900",
            "7. dividend amount": "0.0000"
        },
        "2001-10-31": {
            "1. open": "45.5000",
            "2. high": "54.3500",
            "3. low": "45.1500",
            "4. close": "48.9200",
            "5. adjusted close": "26.8103",
            "6. volume": "119185800",
            "7. dividend amount": "0.2300"
        },
        "2001-09-28": {
            "1. open": "53.7700",
            "2. high": "54.4000",
            "3. low": "35.7500",
            "4. close": "46.3500",
            "5. adjusted close": "25.2853",
            "6. volume": "104867300",
            "7. dividend amount": "0.0000"
        },
        "2001-08-31": {
            "1. open": "60.5000",
            "2. high": "63.8500",
            "3. low": "50.1000",
            "4. close": "53.3500",
            "5. adjusted close": "29.1040",
            "6. volume": "92439700",
            "7. dividend amount": "0.0000"
        },
        "2001-07-31": {
            "1. open": "64.0500",
            "2. high": "64.8300",
            "3. low": "55.3700",
            "4. close": "59.8200",
            "5. adjusted close": "32.6336",
            "6. volume": "80901200",
            "7. dividend amount": "0.2300"
        },
        "2001-06-29": {
            "1. open": "64.8000",
            "2. high": "66.4000",
            "3. low": "55.8200",
            "4. close": "64.2300",
            "5. adjusted close": "34.9133",
            "6. volume": "98334400",
            "7. dividend amount": "0.0000"
        },
        "2001-05-31": {
            "1. open": "62.0000",
            "2. high": "75.2300",
            "3. low": "60.7700",
            "4. close": "65.0100",
            "5. adjusted close": "35.3373",
            "6. volume": "109171300",
            "7. dividend amount": "0.0000"
        },
        "2001-04-30": {
            "1. open": "53.1500",
            "2. high": "68.8500",
            "3. low": "44.1000",
            "4. close": "62.7900",
            "5. adjusted close": "34.1306",
            "6. volume": "144320400",
            "7. dividend amount": "0.2300"
        },
        "2001-03-30": {
            "1. open": "62.5000",
            "2. high": "68.8500",
            "3. low": "49.7000",
            "4. close": "53.5000",
            "5. adjusted close": "28.9338",
            "6. volume": "172595400",
            "7. dividend amount": "0.0000"
        },
        "2001-02-28": {
            "1. open": "85.0500",
            "2. high": "90.4900",
            "3. low": "63.5000",
            "4. close": "65.1300",
            "5. adjusted close": "35.2235",
            "6. volume": "119104600",
            "7. dividend amount": "0.0000"
        },
        "2001-01-31": {
            "1. open": "78.2500",
            "2. high": "89.1900",
            "3. low": "69.0000",
            "4. close": "84.8000",
            "5. adjusted close": "45.8614",
            "6. volume": "136549800",
            "7. dividend amount": "0.2300"
        },
        "2000-12-29": {
            "1. open": "63.2500",
            "2. high": "80.7500",
            "3. low": "61.6200",
            "4. close": "79.2500",
            "5. adjusted close": "42.7456",
            "6. volume": "106375100",
            "7. dividend amount": "0.0000"
        },
        "2000-11-30": {
            "1. open": "77.6200",
            "2. high": "84.2500",
            "3. low": "60.6200",
            "4. close": "63.3800",
            "5. adjusted close": "34.1857",
            "6. volume": "94156800",
            "7. dividend amount": "0.0000"
        },
        "2000-10-31": {
            "1. open": "90.1200",
            "2. high": "93.5000",
            "3. low": "68.2500",
            "4. close": "80.3100",
            "5. adjusted close": "43.3173",
            "6. volume": "118919000",
            "7. dividend amount": "0.2000"
        },
        "2000-09-29": {
            "1. open": "107.5600",
            "2. high": "110.0000",
            "3. low": "85.5000",
            "4. close": "91.4400",
            "5. adjusted close": "49.2117",
            "6. volume": "78678100",
            "7. dividend amount": "0.0000"
        },
        "2000-08-31": {
            "1. open": "92.1200",
            "2. high": "108.5000",
            "3. low": "90.4400",
            "4. close": "107.5800",
            "5. adjusted close": "57.8980",
            "6. volume": "61403500",
            "7. dividend amount": "0.0000"
        },
        "2000-07-31": {
            "1. open": "83.7500",
            "2. high": "97.0000",
            "3. low": "83.5000",
            "4. close": "91.2500",
            "5. adjusted close": "49.1094",
            "6. volume": "55496700",
            "7. dividend amount": "0.2000"
        },
        "2000-06-30": {
            "1. open": "72.0000",
            "2. high": "87.9400",
            "3. low": "70.1200",
            "4. close": "83.2500",
            "5. adjusted close": "44.7010",
            "6. volume": "67563400",
            "7. dividend amount": "0.0000"
        },
        "2000-05-31": {
            "1. open": "76.5000",
            "2. high": "82.6200",
            "3. low": "62.3800",
            "4. close": "71.5000",
            "5. adjusted close": "38.3919",
            "6. volume": "81575700",
            "7. dividend amount": "0.0000"
        },
        "2000-04-28": {
            "1. open": "83.4400",
            "2. high": "90.1900",
            "3. low": "64.7500",
            "4. close": "76.7500",
            "5. adjusted close": "41.2108",
            "6. volume": "91956700",
            "7. dividend amount": "0.2000"
        },
        "2000-03-31": {
            "1. open": "71.8800",
            "2. high": "97.3800",
            "3. low": "71.5000",
            "4. close": "82.8800",
            "5. adjusted close": "44.3910",
            "6. volume": "96506300",
            "7. dividend amount": "0.0000"
        },
        "2000-02-29": {
            "1. open": "65.6200",
            "2. high": "71.1900",
            "3. low": "60.1200",
            "4. close": "70.4400",
            "5. adjusted close": "37.7281",
            "6. volume": "63990900",
            "7. dividend amount": "0.0000"
        },
        "2000-01-31": {
            "1. open": "137.2500",
            "2. high": "138.7500",
            "3. low": "62.5000",
            "4. close": "66.2500",
            "5. adjusted close": "35.4839",
            "6. volume": "48235050",
            "7. dividend amount": "0.4000"
        },
        "1999-12-31": {
            "1. open": "119.5000",
            "2. high": "142.8800",
            "3. low": "119.2500",
            "4. close": "142.7500",
            "5. adjusted close": "38.1122",
            "6. volume": "37401500",
            "7. dividend amount": "0.0000"
        }
    }
}